{"il bagno":"3178874","il cairo":"360630","il maten":"2476412","il matene":"2476412","il matten":"2476412","il'c":"2775324","il'cen":"2820456","il'de re":"3036719","il'eskas":"3120410","il'eus":"3461408","il'ich":"1524138,557292","il'ichevka":"707688","il'ichevo":"557276,1537749","il'ichevsk":"707688,146858","il'ichjovo":"557276","il'ichëvo":"557276","il'inskij pogost":"557132","il'inskij":"557140","il'inskiy pogost":"557132","il'inskiy":"557140","il'insko-podomskoe":"557127","il'insko-podomskoye":"557127","il'inskoe-khovanskoe":"557060","il'inskoe":"557100","il'inskoye-khovanskoye":"557060","il'inskoye":"557127,697953,557140,557100","il'intsy":"707695","il'ja":"627878","il'ka":"2023634","il'menau":"2896514","il'sfel'd":"2896477","il'skaya":"556951","il'skij":"556951","il'skiy":"556951","il'ya":"627878","il'yaly":"601432","il-birgu":"2562966","il-fgura":"2563115","il-furjana":"2562955","il-gharb":"2563063","il-ghasri":"2563052","il-gudja":"2563020","il-gzira":"2562946","il-għarb":"2563063","il-għasri":"2563052","il-gżira":"2562946","il-hamrun":"2562998","il-kalkara":"2562830","il-marsa":"2562755","il-mellieha":"2562744","il-mellieħa":"2562744","il-mosta":"2562704","il-qala":"2562655","il-qrendi":"2562622","ila orangun":"2337765","ila":"2337765","ilabaya":"3938455","ilaca":"3199147","ilacanora":"3695339","iladik":"741892","ilafarda":"2646277","ilagan":"1711146","ilahabad":"1278994","ilahabada":"1278994","ilakha":"2033404","ilakhachzhan":"2033404","ilala":"63344","ilam":"130802,1283333","ilama":"3608860","ilampillai":"1269792","ilan":"1674199","ilanc":"2660275","ilancsa":"790028","ilandza":"790028","ilandža":"790028","ilangay":"1711135","ilangea":"790028","ilanskij":"1505933","ilanskiy":"1505933","ilanskoe":"1505933","ilanskoye":"1505933","ilantan":"2643743","ilanz":"2660275","ilara":"2337762","ilare":"2337762","ilaro":"2337759","ilasan ilaya":"1711128","ilasan":"1711128","ilashan-jurt":"577883","ilasi":"675810","ilaskhan-jurt":"577883","ilaskhan-yurt":"577883","ilasxan-yurt":"577883","ilata":"295277","ilava":"3059796,3097902","ilave":"3938451","ilawa":"3097902","ilaya":"3608828,1711119,1679476","ilayang calilayan":"1720316","ilañgay":"1711135","ilača":"3199147","ilba":"675684","ilberstedt":"2896602","ilbesheim":"2896600","ilbono":"2524530","ilcen":"2820456","ilche":"3120417","ilchester":"2646279,4358864","ild":"3118514","ile d'abeau":"2998136","ile de groix":"3014579","ile de murano":"3172456","ile de re":"3036719","ile rousse":"2998330","ile-de-la-republique":"2978361","ile-de-la-république":"2978361","ile-republicaine":"3036719","ile-républicaine":"3036719","ile-tortue":"2967549","ile":"8299862,4703223","ileana":"675683","ileanda":"675678","ilebo":"215976","ilek":"557340","ilela":"878087","ilella":"2443304","ilembo":"159219","ilembula":"159218","ilen-gorodok":"557340","ilenurme":"588092","ilerda":"3118514","ilerdo":"3118514","ilertisen":"2896546","ilertiseno":"2896546","iles":"3680616","ilesa":"2337704","ilesha":"2337704","ilet'":"542366","iletsk":"491019","iletskaya zashchita":"491019","iletskaya zashkta":"491019","iletskaya":"491019","iletski gordok":"557340","ilet’":"542366","ileukucheukeu":"2023469","ileza":"829291","ilezk":"491019","ilfeld-wiegersdorf":"2896592","ilfeld":"2896592","ilfentig":"3012905","ilfinieg":"2967234","ilford":"2646277","ilfracombe":"2646276","ilg":"4145381","ilgaz":"745344","ilgin":"311553","ilgın":"311553","ilh":"2896543","ilha das cotias":"3393929","ilha das cutias":"3393929","ilha de mocambique":"1037390","ilha de moçambique":"1037390","ilha solteira":"3461411","ilhabela":"3461425","ilhavo":"2738707","ilheos":"3461408","ilheus":"3461408","ilhéos":"3461408","ilhéus":"3461408","ili diqu":"1529435","ili-i":"630952","ili":"1519948,1529443,1643160,2650023,5188843","ilia":"627878,675670","iliande":"2660275","ilias":"3199142","iliaš":"3199142","ilic":"311547","ilica":"311535,311538,311533","ilicalar":"311538","ilich":"146858","ilici":"3213083,311533","ilieni":"675664","iligan city":"1711082","iligan":"1711082","ilihan":"1711073,1711061","iliinoe-podomskoe":"557127","iliisk":"1519948","ilijan":"1711061","ilijas":"3199142","ilijaš":"3199142","ilijek":"1519948","ilikiminki":"630918","ilinden":"833357","ilinga":"2650567","ilinge":"994939","ilino podomskoe":"557127","ilinskij pogost":"557132","ilinsko-podomskoje":"557127","ilinskoje-khovanskoje":"557060","ilinskoje":"557100","ilioilio":"1711047","ilion":"256601,5121765","ilioupoli":"8310138","ilioúpoli":"8310138","ilir":"2023638","ilirska bistrica":"3199131","ilisesti":"675652","iliskhan-jurt":"577883","ilisxan-yurt":"577883","ilitsj":"557292","ilitsjevo":"557276,1537749","ilivieska":"630768","ilivileq":"3421765","iliya":"627878","iliysk":"1519948","iliyskoye":"1519948","ilići":"3213083","ilişeşti":"675652","ilișești":"675652","ilja":"627878","ilka":"2023634","ilkal":"1269784","ilkeston":"2646274","ilkley":"2646272","ill":"5052916","illa":"3012848","illan de vacas":"2516457","illana":"3120414","illancs":"790028","illancsa":"790028","illange":"3012854","illano":"3120413","illapel":"3887344","illar":"2516456","illas":"3120412","illasi":"3175584","illats":"3012851","illava":"3059796","ille-sur-la-tet":"3012848","ille-sur-tet":"3012848","ille-sur-têt":"3012848","ille":"303502,3012848","illela":"2443304,2337680","illerich":"2896548","illerrieden":"2896547","illertissen":"2896546","illescas":"3120410","illesheim":"2896543","illeta":"2443304","illfurth":"3012845","illi":"2650023,5503694","illichivs'k":"707688","illichivs’k":"707688","illici":"2518559","illies":"3012837","illinci":"707695","illingen":"2896539,2896538","illintsi":"707695","illizi":"2493456","illkirch-graffenstaden":"3012834","illkirch":"3012834","illmensee":"2896530","illmic":"2775327","illmitz":"2775327","illnau / unter-illnau":"2658249","illnau":"2660269","illora":"2516455","illorai":"3175575","illorin":"2337639","illschwang":"2896523","illueca":"3120407","illuppur":"1269782","illushi":"2337666","illyrisch feistritz":"3199131","illzach":"3012829","illán de vacas":"2516457","illéla":"2443304","illéta":"2443304","ilm":"4499379","ilmajoki":"656739","ilmenau":"2896514","ilminster":"2646265","ilmmunster":"2896506","ilmmünster":"2896506","ilmola":"656739","iln":"4528463","ilo":"1711005,3938415","ilobu":"2337659","ilog":"1711030","iloh":"321836","iloilo city":"1711005","iloilo proper":"1711005","iloilo":"1711005","ilok":"3199128","ilomants":"656709","ilomantsi":"656709","ilonc":"790028","iloncz":"790028","ilondon":"2643743","ilongero":"159186","ilopango":"3585484","ilorin":"2337639","ilosva":"707559","ilovaiskaia":"707679","ilovajsk":"707679","ilovat":"675642","ilovatu":"675642","ilovatul":"675642","ilovays'k":"707679","ilovayskaya":"707679","ilovays’k":"707679","ilovica":"790018,675637","ilovita":"675637","iloviţa":"675637","ilovka":"556967","ilovlinska":"556961","ilovlinskaya":"556961","ilovlja":"556961","ilovlya":"556961","ilovskoye":"556967","ilovăţ":"675642","ilovăţu":"675642","ilovăţul":"675642","ilovăț":"675642","ilow":"770798","ilowa":"3097896","ilowo -osada":"7534560","ilq":"3938415","ilquilisco":"3585438","ilr":"2337639","ilsede":"3208606","ilsenburg":"2896483","ilsfeld":"2896477","ilshofen":"2896476","ilskij":"556951","iltracombe":"2646276","ilu kansas":"4393217","iluh":"321836","iluka":"6697153","ilukste":"459586","ilula":"159179","ilulisat":"3423146","ilulissat":"3423146","ilunberri":"3117804","iluppur":"1269782","iluppūr":"1269782","iluro":"2521840,3117164","ilva mare":"675632","ilva mica":"675629","ilva mică":"675629","ilvesheim":"2896468","ilyanli":"601432","ilyasbey":"745308","ilyasli":"311469","ilyefalva":"675664","ilyich":"1524138","ilyitschovsk":"707688","ilz":"2775324,3056508","ilza":"770792","ilzha":"770792","iláncsa":"790028","ilāhābād":"1278994","ilām":"1283333","ilıca":"311535,311538,311533","ilıcalar":"311538","ilūkste":"459586","ilža":"770792","il’ich":"557292","il’ichevka":"707688","il’ichevo":"1537749","il’ichevsk":"707688","il’ichëvo":"557276","il’ichëvsk":"707688,146858","il’inskiy pogost":"557132","il’inskiy":"557140","il’insko-podomskoye":"557127","il’inskoye-khovanskoye":"557060","il’inskoye":"557127,557140,557100","il’intsy":"707695","il’ka":"2023634","il’skaya":"556951","il’skiy":"556951","il’ya":"627878","il’yaly":"601432"}