{"is poselok":"556131","is suieki":"2562850","is-sannat":"2562545","is-siggiewi":"2562504","is-siġġiewi":"2562504","is-sur-tille":"3012652","is-swieki":"2562850","is-swieqi":"2562850","is":"556131,3012652","isa town":"290187","isa":"2065594,290187","isaac arriaga (santa ana mancera)":"4025025","isabang":"1710526","isabel segunda":"4565575","isabel":"1710523,1710519","isabela city":"1710519","isabela":"1710518,4565577,1710519","isabella":"1710518","isabeyli":"311214","isaccea":"675495","isad-sel'tso":"555794","isad-sel’tso":"555794","isady":"497242","isafiordr":"3415667","isafjardardjup":"3415667","isafjoerdur":"3415667","isafjordur":"3415667","isagarh":"1269685","isahara":"1861464","isahaya":"1861464","isak":"1215014","isaka":"159045,5122432","isakcha":"675495","isakli":"300201,311183","isakly":"556111","isal'mi":"656820","isalamabada":"1176615","isalmi":"656820","isalnita":"675489","isangel":"2136825","isanlu itedoijowa":"2337235","isanti":"5031489","isaq":"1215014","isar":"3120292","isara":"2337227,3461519","isaratov":"498677","isasca":"6535862","isasi":"158825","isasondo":"3120289","isaszeg":"3051077","isawa":"1861454","isb":"1176615","isbarta":"311073","isbergues":"3012725","isbiceni":"675407","isbischte":"789972","isca dell'ionio":"2524501","isca dello ionio":"2524501","isca dello iónio":"2524501","isca sull'ionio":"2524501","isca sullo ionio":"2524501","isca":"2524501","iscande":"3680491","iscandé":"3680491","iscar":"3120288","iscehisar":"311193","ischewsk":"554840","ischgl":"2775183","ischi":"2782052","ischia di castro":"3175454","ischia porto":"3175453","ischia":"3175458","ischim":"1505453","ischitella":"3175452","ischl":"2782052","iscia baidoa":"64536","iscla":"3175458","iscroni":"675483","iscuande":"3680491","iscuandé":"3680491","isdalssto":"3151001","isdalsstø":"3151001","isdalsto":"3151001","isdalstø":"3151001","ise si":"1861450","ise-ekiti":"2337207","ise":"1861450,311073,2337207","isebay":"504391","iseghem":"2795009","iseh":"1861450","isehara":"1861449","iselin":"5099738","isembai":"555980","isen":"2895702","isena":"2895702","isenburg":"2895689","isenbuttel":"2895688","isenbüttel":"2895688","isenheim":"3012671","isenye":"158974","iseo":"3175447","isera":"6534997","iseredinabuda":"694491","iserlaun":"2895669","iserlohn":"2895669","iserlon":"2895669","isernhagen farster bauerschaft":"2895664","isernia":"3175445","isert":"2895659","isesaki":"1861436","iset'":"1505472","iset":"1505472","isetskoe":"1505466","isetskoje":"1505466","isetskoye":"1505466","iset’":"1505472","iseullamabadeu":"1176615","iseuteon":"5188140","iseuteukilbeulaideu":"2650405","iseuteula":"555746","iseuteulaensing":"4991640","iseuteuleodeopeodeu":"5097459","iseuteuleondeon":"1006984","iseuteuloseuaenjelleseu":"5344994","isezaki":"1861436","isfahan":"418863","isfakhan":"418863","isfana":"1222662","isfara":"1514896","isfina":"1222662","isg":"1861416","isgoren":"311191","ish":"3175458","isha baydabo":"64536","isha baydhaba":"64536","isha baydhabo":"64536","ishakli":"300201,311183","ishanova":"1486525","ishara":"2337227","ishcherskaya":"555994","isheevka":"555984","ishem":"3185351","isherskaya":"555994","ishewsk":"554840","isheyevka":"555984","ishherskaja":"555994","ishi":"1786458","ishi=re=murino":"3012649","ishigachi":"1861416","ishigaki":"1861416","ishige":"1861406","ishii":"1861400","ishikari":"2129909","ishikawa":"2112583,1861393","ishiki":"1861383","ishim":"1505453","ishimbaj":"555980","ishimbay":"555980","ishinomachi":"2112576","ishinomaki":"2112576","ishioka":"2112571","ishiza":"1861393","ishkashim post":"1221614","ishkashim":"1221614","ishkhoj-jurt":"555962","ishkhojn-ehvla":"555962","ishkhojn-jurt":"555962","ishkhoy-yurt":"555962","ishkāshīm post":"1221614","ishkˌobod":"162183","ishlei":"555950","ishlej":"555950","ishley-pokrovskoye":"555950","ishley":"555950","ishm":"3185351","ishma":"554830","ishmi":"3185351","ishnja":"555933","ishnya":"555933","ishoj-jurt":"555962","ishoj":"2619377","ishpeming":"4997281","ishqoshim":"1221614","ishtib":"785482","ishtihon":"1217215","ishtikhon":"1217215","ishtixon":"1217215","ishtykhan":"1217215","ishuatan":"3526769","ishuatán":"3526769","ishurda":"1185207","ishurdi":"1185207","ishëm":"3185351","ishøj":"2619377","isi le mulino":"3012649","isiangulovo":"555717","isidoro noblia":"3442299","isidoro noblía":"3442299","isieke":"2337148","isigaki":"1861416","isigny-le-buat":"3012713","isigny-sur-mer":"3012712","isigny":"3012713","isii":"1861400","isikari":"2129909","isikava":"2112583,1861393","isiklar":"311159,439221","isilemollino":"3012649","isiles":"3177326","isili":"2524498","isim":"1505453","isimbai":"555980","isimbaj":"555980","isimoe":"1642996","isimu":"1642996","ising":"1718337","isingiro":"7911405","isinomaki si":"2112576","isinomaki":"2112576","isio":"1730097","isioka":"2112571","isiolo":"196231","isirio":"215771","isiro":"215771","isj":"3526756","isjangulovo":"555717","isjim":"1505453","isjkhoj-jurt":"555962","isjlej":"555950","isjnja":"555933","isjtsjerskaja":"555994","isk'ja":"3175458","iskan":"305686","iskandar":"1513900","iskandariah":"361058","iskandariya":"361058","iskandariyah":"361058,311111","iskander":"1513900","iskanderun":"311111","iskatelej":"866062","iskateley":"866062","iskefiye":"749701","iskele":"146027,304204","iskelib":"745076","iskenderiye":"361058","iskenderon":"311111","iskenderun":"311111","iski-tashkent":"1514027","iskilip":"745076","iskindiriya":"361058","iskindirîya":"361058","iskitim":"1505429","iskodra":"3184081","iskur":"728348","iskushuban":"56505","iskŭr":"728348","isla aguada":"3526766","isla bastimentos":"3714260","isla cabello":"3443697","isla cabellos":"3443697","isla cristina":"2516431","isla de aguada":"3526766","isla de bastimentos":"3714260","isla de cabellos":"3443697","isla de capri":"3180630","isla de fehmarn":"8051091","isla de palmito del verde":"3993774","isla de taquili":"3927803","isla del bosque":"3976232","isla del sol":"3913985","isla favignana":"2524780","isla gallinazo":"3704029","isla mala":"3439659","isla mujeres":"3526756","isla provision":"3714260","isla provisión":"3714260","isla pucu":"3437962","isla pucú":"3437962","isla soyaltepec":"3801262","isla verde":"3853643","isla vista":"5359864","isla-kristina":"2516431","isla":"1710489,2562792,3525596,3012709","islahiye":"311104","islam kala":"1142404","islam killa":"1142404","islam qal`ah":"1142404","islam qala":"1142404","islamabad":"1176615,1278667,1205733","islamabada":"1176615","islamabadas":"1176615","islamabade":"1176615","islamabadi":"1176615","islamabado":"1176615","islamahbad":"1176615","islamampant":"1176615","islamapat":"1176615","islamej":"537344","islamey":"537344","islamic city of marawi":"1701053","islamkot":"1176608","islamkoy":"322051","islamli":"735679","islamlí":"735679","islamnagar":"1269670","islamorada":"4159839","islampur":"1269665,1269666","island harbour":"3573456","island heights":"4502420","island lake":"4897579","island park":"5122397","islandia":"5122409","islas agrarias grupo a":"3979569","islas agrarias":"3979569","islay":"8299862","islaz":"675480,675479","islazu":"675480","islazul":"675480","isle of arran":"8299836","isle of barra":"8299866","isle of benbecula":"8299868","isle of bute":"8299622","isle of cumbrae":"8299852","isle of harris":"8299859","isle of hope":"4202308","isle of islay":"8299862","isle of lewis":"8299620","isle of mull":"7290043","isle of north uist":"8299849","isle of palms":"4583114","isle of portland":"6692041","isle of skye":"8299863","isle of south uist":"8299850","isle of wight":"4766204","isle sur sorgue":"2998127","isle-d'abeau":"2998136","isle":"3012709","isleham":"2646012","isles of scilly":"8299858","isleworth":"2646004","islimiye":"727079","islimje":"727079","islington":"3489962,2646003","islip terrace":"5122417","islip":"5122413","isliten":"2208485","islàmabad":"1176615","islámábád":"1176615","islām kala":"1142404","islām qala":"1142404","islām qal‘ah":"1142404","islāmkot":"1176608","islāmnagar":"1269670","islāmpur":"1269665,1269666","islāmābād":"1176615","islāmābāda":"1176615","islīten":"2208485","ismail":"707308","ismailia":"361055","ismailieh":"361055","ismailija":"361055","ismailiya":"361055","ismailiyah":"361055","ismailli":"311078","ismailly":"586318","ismaily":"586318","ismailîya":"361055","ismajil":"707308","ismaning":"2895643","ismanlli":"586318","ismayilli":"586318","ismayylly":"586318","ismaïlia":"361055","ismetpasa":"296791","ismid":"745028","ismir":"311046","ismit":"745028","ismoili somon":"1220862","ismoili somoni":"1220862","ismoili somoní":"1220862","ismoylly":"586318","isn":"5692947","isna":"355449","isneauville":"3012698","isneddu":"2524496","isnello":"2524496","isni im algoj":"2895638","isni":"2895638","isnik":"745026","isnimid":"745028","isniq":"790002","isniqi":"790002","isnos":"3792389","isny im allgau":"2895638","isny im allgäu":"2895638","isny":"2895638","isnā":"355449","iso":"4474436","isobol":"3120272","isojoki":"656517","isoka":"916668","isokyro":"656456","isokyroe":"656456","isokyrö":"656456","isol'ye-sibirskoye":"2014022","isola capo rizzuto":"2524495","isola d'asti":"6534388","isola d'istria":"3199017","isola del cantone":"3175430","isola del giglio":"6534705","isola del gran sasso d'italia":"3175429","isola del gran sasso":"3175429","isola del liri":"3175427","isola del piano":"3175426","isola della scala":"3175428","isola delle femmine":"2524494","isola di capo rizzuto":"2524495","isola di capri":"3180630","isola di curzola":"3197710","isola di fondra":"6534508","isola di liri":"3175427","isola di pago":"3193726","isola di unalaska":"5877208","isola dovarese":"3175424","isola d’istria":"3199017","isola rizza":"6535574","isola rossa":"2998330","isola sant'antonio":"3175415","isola vicentina":"3175414","isola":"3175429,2524495,3193782,3199017","isolabella":"6535397","isolabona":"3175433","isole tremiti":"6534807","isol’ye-sibirskoye":"2014022","isonidhion":"258500","isonidion":"258500","isonídhion":"258500","isonídion":"258500","isorella":"3175408","isovol":"3120272","isowaru":"3012664","isp":"5122413","ispahan":"418863","ispani":"6535553","isparta":"311073","ispartah":"311073","ispas":"707529","ispendere":"318141","isperich":"730866","isperih":"730866","isperikh":"730866","ispica":"2524493","ispir":"745047","ispra":"3175406","ispravnaja":"555801","ispravnaya":"555801","ispringen":"2895636","isq":"5000625","isques":"3012688","isrutis":"568595","iss":"4983359","issa":"555798","issad":"555794","issafjordur":"3415667","issafjörður":"3415667","issaquah":"5798487","isse":"3012676","isseksi":"2545436","issel'stejn":"2753355","isselbach":"2895631","isselburg":"2895630","issenheim":"3012671","issenye":"158974","isser":"2492991","isseroda":"2895623","issersheilingen":"2895622","isserville":"2492991","isshiki":"1861383","issi-le-mulino":"3012649","issia":"2287790","issigau":"2895619","issiglio":"6535398","issime":"3175405","issingeaux":"2967203","isso":"6535172","issogne":"3175403","issoire":"3012664","issok":"1523741","issou":"3012656","issoudun":"3012655","issuar":"3012664","issuden":"3012655","issum":"2895617","issy-les-moulineau":"3012649","issy-les-moulineaux":"3012649","issy":"3012649","issyk-kul'":"1527004","issyk-kul’":"1527004","issyk":"1523741","issé":"3012676","issök":"1523741","ist khaddam":"4833363","ist khartford":"4833403","ist khehven":"4833425","ist kilbrajd":"2650405","ist lansing":"4991640","ist liverpul'":"5152709","ist providens":"5221931","ist raderfornt":"5097459","ist ruzehrford":"5097459","ist uinachi":"5793271","ist venachi":"5793271","ist-kilbrajd":"2650405","ist-lansing":"4991640","ist-london":"1006984","ist-providens":"5221931","ist-raterford":"5097459","ist-rezerford":"5097459","ist":"745044","ista landana":"1006984","ista tvikanahama":"2635308","istad":"2662149","istadas":"2662149","istadium":"2662149","istaguacan":"3595282","istaguacán":"3595282","istalef":"1142330","istalif":"1142330","istamboul":"745044","istambul":"745044","istambuł":"745044","istampoul":"745044","istan":"2516421","istanbul":"745044","istanbúl":"745044","istanos":"306474","istapa":"3595255","istaravshan":"1220253","istborn":"2650497","istbornas":"2650497","istebna":"3097865","istebno":"3097865","isterberg":"3208432","isterek":"791948","istgah-e garmsar":"32723","istgah-e rah ahan garmsar":"32723","istgah-e rah ahan-e garmsar":"32723","isthmia":"261721","isthmos":"261721","isthmía":"261721","isthmós":"261721","istiaia":"261720","istiaía":"261720","istibulagh":"616627","istifan":"751516","istilif":"1142330","istilil":"325028","istintino":"3166134","istip":"785482","istkhehm":"4935578","istli":"2650396","istmia":"3680453","istmina":"3680453","istmino":"3680453","istochni london":"1006984","istog":"789996","istogu":"789996","istok":"789996,2023427,1536648","iston":"5345171,4935623,4353962,4963478,5188140","istonio":"3164672","istport":"4963486","istr":"3012647","istra":"555746,3012647","istrana":"3175398","istras":"3012647","istre":"3012647","istres":"3012647","istria":"675471","istrus":"675471","istvanfalva":"679716","istvanfold":"789124","istvanfolde":"789124","istvanvolgy":"790063","istvánfalva":"679716","istvánföld":"789124","istvánfölde":"789124","istvánvölgy":"790063","istán":"2516421","istālef":"1142330","istālif":"1142330","isudan":"3012655","isudjon":"3012655","isuerre":"3120263","isugod":"1710473","isula":"2524494","isulan":"1710470","isungwi":"153759","isuramabado":"1176615","isutaddo":"2662149","isutanburu":"745044","isutobon":"2650497","isutogurinsuteddo":"2650435","isuton":"5188140","isutopurobidensu":"5221931","isutoranshingu":"4991640","isutorazafodo":"5097459","isutorosanzerusu":"5344994","isutoru":"3012647","isutowanatchi":"5793271","isverna":"675462","isvoare":"675395","isvoarele sucevii":"675365","isvoarele":"675385,675387,675389,675391","isvor":"675365","isvoru-de-sus":"675352","isvorul de sus":"675326,675352","isvorul-dulce":"675321","isvorul":"675365","isw":"5279436","isxoyn-avla":"555962","isxoyn-evla":"555962","isxoyn-yurt":"555962","isyangulovo":"555717","iszlamabad":"1176615","iszlámábád":"1176615","isztambul":"745044","iszymbaj":"555980","isérnia":"3175445","isìles":"3177326","isòvol":"3120272","isóbol":"3120272","isāgarh":"1269685","isė":"1861450"}