{"no kunda":"2412355","no wo sibiskh":"1496747","no'eda":"7279746","no'ida":"7279746","no-ho-chen":"2035610","no-ho-hsien":"2035610","no-ho":"2035610","no-mo-hung-ho-t'o":"1280432","no-mo-hung-ho-t’o":"1280432","no-mo-hung":"1280432","no-mu-hung":"1280432","noa":"2154787,7414453","noaillan":"2990311","noailles":"2990307","noajon":"2989877","noal-ar-gwilen":"2989914","noal-muzilheg":"2989920","noal-pondivi":"2989918","noale":"3172252","noalejo":"2513217","noamundi":"1261242","noan chanta":"1608524","noank":"4839568","noapels":"3172394","noardburgum":"2749992","noardwalde":"2749807","noardwâlde":"2749807","noare":"3172252","noarlunga centre":"2064655","noarlunga":"2064655","noasca":"3172251","noasuka":"3172251","noazi le gran":"2990189","nobagolicha":"3194452","nobdenitz":"2862326","nobeoka":"1855095","nobic":"2862322","nobinobi":"8403438","nobipajaleu":"787595","nobisadeu":"3194360","nobisongchi":"763534","nobitz":"2862322","noble":"4543733","nobleboro":"4973402","noblejas":"2513216","noblesville":"4924198","nobnkoront":"519336","nobo":"1633907","noboaltaiseukeu":"1497173","nobochebogsaleuseukeu":"518976","nobocheleukaseukeu":"518970","nobodeubinseukeu":"518909","nobokujeunecheukeu":"1496990","nobolosiseukeu":"518255","nobomoseukobseukeu":"518557","noborosisk":"518255","nobosibileuseukeu":"1496747","nobosimpirsk":"1496747","nobres":"3456277","nobsa":"3673829","nobulsvil":"4924198","noburuzubiru":"4924198","nocaima":"3673826","nocajski salas":"3191339","nocara":"3172250","nocatee":"4166047","nocciano":"3172249","nocera inferiore":"3172244","nocera superiore":"3172243","nocera terinese":"2524000","nocera tirinese":"2524000","nocera umbra":"3172242","nocera":"3172244","noceto":"3172241","nochathel":"2659496","nochern":"2862319","nochi":"3172240","nochistlan":"3532656,3994912","nochistlán":"3994912","nochixtlan":"3532656","nochling":"2770472","noci":"3172240","nociglia":"3172239","nocilia":"3172239","nocona":"4714865","nocrich":"672176","nocupetaro":"3994911","nocupétaro":"3994911","noda":"1855078,2862311,2126250","nodasamu":"2126250","nodasan":"2126250","nodebo":"2616423","nodeland":"3144534","nodendal'":"645211","nodinge-nol":"3336569","nodoa":"1800234","noe":"2990294","noea ulma":"2863941","noebana":"8418279","noebesa":"8403423","noedinge-nol":"3336569","noehawaila":"1633843","noehawala":"1633843","noeiswileusen":"2990611","noel":"4400673","noeltoko":"1633904","noemba":"1633828","noemberjan":"616333","noemoeti":"1633903","noemuti":"1633903","noen kham":"1155989","noen maprang":"1608371","noen sa-nga":"7510950","noen sala":"1609379","noenoni":"1633896","noepoli":"3172236","noer":"2862304","noerden":"2862118","noerdlingen":"2861914","noerten-harenbarg":"2861817","noesaherang":"8054260","noesyatel":"2659496","noeteborg":"493970","noetinger":"3843026","noeux-les-mines":"2990287","noeyon":"2989877","noez":"2513215","nof ayalon":"8199379","nofels":"2770464","nofoali`i":"4035174","nofoali‘i":"4035174","nofoku":"4776222","nog orlean":"4335045","nog":"4004886","nogaisk":"696292","nogaj-mirza-jurt":"571702","nogal de las huertas":"3115409","nogales":"4004886,3522696,2513214,5306611","nogamerzin-jurt":"571702","nogamerzin-yurt":"571702","nogamirzin-yurt":"571702","nogara":"3172235","nogaredo":"6534631","nogaro":"2990284","nogarole di rocca":"3172232","nogarole rocca":"3172232","nogarole vicentino":"6535584","nogata":"1855066","nogay-mirza-yurt":"571702","nogay-mirza":"571702","nogaysk":"696292","nogent-haute-marne":"2990276","nogent-le-bas":"2990276","nogent-le-phaye":"2990274","nogent-le-republicain":"2990272","nogent-le-roi":"2990273","nogent-le-rotrou":"2990272","nogent-le-républicain":"2990272","nogent-roullebois":"2990273","nogent-sur-marne":"2990265","nogent-sur-oise":"2990264","nogent-sur-seine":"2990263","nogent-sur-vernisson":"2990261","nogent":"2990274,2990263,2990265,2990264","nogentel":"2990281","noghinsk":"520068","nogiamirzin-jurt":"571702","nogins'k":"520068","noginseukeu":"520068","noginsk-9":"7601828","noginsk":"520068","noginska":"520068","noginskas":"520068","noginsuku":"520068","nogir":"520065","nogińsk":"520068","noglik":"2122783","nogliki":"2122783","nogon-nur":"1515468","nogoonnuur":"1515468","nogosari":"1633900","nogradveroce":"3042956","nogseubil":"4634946","nogtsard":"499404","nogueira da regedoura":"2737137","nogueira de ramuin":"3115394","nogueira de ramuín":"3115394","nogueira":"2737137,2737150,3115394","nogueras":"3115386","nogueroles":"3115383","nogueruelas":"3115383","noguinsk":"520068","nohanent":"2990257","nohar":"1261234","nohen":"2862295","nohfelden":"2862294","nohic":"2990250","nohn":"2862292","nohor tehsils":"1261234","nohra":"2862289","noia":"3115331","noiant":"2989913","noibeulandenbuleukeu":"2866135","noibrandenburgas":"2866135","noiburandenburuku":"2866135","noicattaro":"3172228","noida":"7279746","noidans-les-vesoul":"2990247","noidans-lès-vesoul":"2990247","noidans":"2990247","noiendetteruzau":"2865798","noilnoni":"1633896","noiltoko":"1633904","noilupin":"2864276","noimwinseuteo":"2864475","noimyunsuta":"2864475","noin somon":"2030465","noing":"1697607","noinkirchenas":"2864435","nointot":"2990240","noireau":"3023953","noiretable":"2990214","noirmont":"2659955","noirétable":"2990214","noiseau":"2990195","noisiel":"2990192","noisy-le-grand":"2990189","noisy-le-roi":"2990188","noisy-le-sec":"2990187","noisy-sur-ecole":"2990185","noisy-sur-école":"2990185","noisy":"2990189","noizay":"2990183","noj-izenburg":"2864820","noj-ul'm":"2863941","noj-ulm":"2863941","noja":"3115376","nojabr'sk":"1496503","nojakert":"174805","nojan=shuru=marunu":"2990265","nojbrandenburg":"2866135","nojbrandenburge":"2866135","nojburg na dunavu":"2866070","nojburg-an-der-donau":"2866070","nojburg-na-dunae":"2866070","nojda":"7279746","nojditendorf":"2866009","nojenburg am rajn":"2865813","nojenburg-na-rejne":"2865813","nojendetelzau":"2865798","nojendettel'zau":"2865798","nojenrade":"2865592","nojenshtadt-am-kokher":"2865560","nojenshtat am kokher":"2865560","nojfel'd-an-der-lajte":"2770788","nojkhaus am renveg":"2865133","nojkhaus na renveg":"2865133","nojkhaus-am-renveg":"2865133","nojkhaus-na-renvege":"2865133","nojkhofen-na-ibbse":"2770749","nojkirkhen-am-grosfenediger":"2770740","nojkirkhen-an-der-fjokla":"2770736","nojmarkt in der oberpfalc":"2864549","nojmarkt-am-vallerzee":"2770727","nojmarkt":"2864549","nojminster":"2864475","nojmjunster":"2864475","nojnkirkhen":"2864435","nojorid":"672171","nojrupin":"2864276","nojruppin":"2864276","nojs":"2864118","nojshhat an der vajnshhrase":"2864054","nojshtadt-am-rjubenberge":"2864058","nojshtadt-an-der-vajnshtrasse":"2864054","nojshtadt-gleve":"2864036","nojshtadt-koburg":"2864053","nojshtadt-na-ajshe":"2864057","nojshtadt-na-ajshi":"2864057","nojshtadt-na-dunae":"2864056","nojshtadt-na-val'dnabe":"2864055","nojshtadt":"2864091,2864054,2864034,2864089,2864072","nojshtat am ribenberge":"2864058","nojshtat an der ajsh":"2864057","nojshtat an der vajnshtrase":"2864054","nojshtat baj koburg":"2864053","nojshtat in kholshtajn":"2864034","nojshtat na dunavu":"2864056","nojshtat na valdnabu":"2864055","nojshtat-gleve":"2864036","nojshtift":"2770651","nojshtrelic":"2864005","nojshtrelice":"2864005","nojstift-na-lafnice":"2770659","nojstrelic":"2864005","nojvid":"2863840","nojzidl am zee":"2770684","nojzidl na jezeru":"2770684","nojzidl'-am-ze":"2770684","nojzidl'-am-zee":"2770684","nojzidl'-an-der-cajja":"2770679","nojzidul am zee":"2770684","nojštrelic":"2864005","nok bride":"2963105","noka":"1261227","nokanen":"933211","nokaneng":"933211","nokaning":"933211","nokesville":"4776181","nokha mani":"1261227","nokha":"1261227","nokhamandi":"1261227","nokia stad":"644450","nokia":"644450","nokkeushi":"2129537","nokkeusi":"2129537","nokkusubiru":"4634946","nokomis":"4166049,4245744","noksvil":"4634946","noksvill":"4863705,4898734,4634946","nokuy":"2021908","nol-sur-moselle":"2981808","nola":"3172227,2383827","nolanville":"4714895","nolay":"3115374,2990177","nolby":"2689520","noldau":"3100193","nole canavese":"3172226","nole":"3172226","nolensville":"4645738","noleusyeping":"2688368","noleuteuhaujen":"2861982","noli":"3172225","nolichi":"4839843,2641181","noling":"1697439","nolinsk":"520041","noliseutaun":"5203506","nom hoy":"1811103","nom pen":"1821306","nom":"5870133","noma":"5870133","nomaglio":"3172222","nomain":"2990167","noman":"4543762","nomantag":"1715212","nomario":"3172222","nomaz-jurt":"571702","nomaz-yurt":"571702","nombela":"3115373","nomborn":"2862249","nombre de dios":"3994863","nombre de jesus":"3604414","nombre de jesús":"3604414","nombre jesus":"3604414","nombre jesús":"3604414","nombrevilla":"3115372","nome":"5870133","nomea":"2139521","nomeny":"2990164","nomeon":"4543762","nomexy":"2990163","nomgon":"2029816","nomhom":"1280432","nomhon":"1280432","nomi":"3172220","nomih":"8392399","nommay":"2990162","nomme":"591381","nomochon-choto":"1280432","nomokhan khoto":"1280432","nomorge":"1515762","nomorgo suma":"1515762","nomos kastorias":"735927","nomos kilkis":"735736","nomos rethymnes":"254352","nomos trikalon":"252664","nompani":"3995529","nompaní":"3995529","nomrog":"1515762","nomu":"5870133","nomwin":"7644931","non buri":"1608133","non chan":"1608524","non daeng":"7510961","non din daeng":"7510956","non kho":"1608142","non khun":"1608142","non khx":"1608142","non narai":"7510986","non narayn":"7510986","non rawiang":"1608267","non sa-at":"1608140","non sang":"1608139","non sila":"7510964","non sung":"1608136","non suwan":"1599410","non suwrrn":"1599410","non thai":"1608131","nona":"3194492","nonancourt":"2990158","nonantola":"3172217","nonantora":"3172217","nonaspe":"3115370","nondaburi":"1608133","nondha buri":"1608133","none":"3172215","nong an":"2035565","nong ba zhen":"8399539","nong ba":"8399539","nong bua daeng":"7510938","nong bua lamphu":"1608269","nong bua rawe":"1608267","nong bua":"1608286","nong buaraheo":"1608267","nong buk":"1608531","nong bun nak":"1608266","nong chang":"1151730","nong che xiang":"1941108","nong chik":"1608263","nong chok":"1608258","nong don":"1615758","nong hai":"1608232","nong han":"1608251","nong he zhen":"2035563","nong he":"2035563","nong hi":"1600444","nong hin":"1600435","nong hong":"1608247","nong kai":"1608232","nong kha yang":"1151710","nong khae":"1608239","nong khaem":"1608236","nong khai":"1608232","nong ki":"1608222","nong kradi":"1150210","nong kung si":"1595679","nong luang":"1151710","nong mamong":"1155740","nong mu":"1605022","nong muang khai":"1615380","nong muang":"1600129","nong na kham":"1600104","nong phai":"1608191","nong phok":"1608188","nong prue":"7510878","nong ri":"1280978","nong rua":"1608177","nong ruea":"1608177","nong saeng":"1608174,1608173","nong sua":"1608163","nong suea":"7510911","nong sung":"1608160","nong te long":"2990140","nong waeng":"1610185","nong wua so":"7510968","nong ya plong":"1151664","nong yai":"1608148","nong yasai":"7510891","nong'an":"2035565","nong-kkhaj":"1608232","nongba zhen":"8399539","nongba":"8399539","nongchang":"1788730","nongche xiang":"1941108","nonggunong":"8408284","nonghe zhen":"2035563","nonghe":"2035563","nonghui":"1799194","nongkesan":"8392369","nongkosewu":"7081818","nongoma":"970133","nongpoh":"1261208","nongri":"1280978","nongstoin":"1261205","nong’an":"2035565","nonio":"6535735","nonkai":"1608232","nonnenhorn":"2862202","nonnweiler":"2862174","nonohonis":"8402917","nonoichi":"1854979","nonpuah":"8391472","nonsan":"1840211","nonsang":"1608139","nonsansi":"1840211","nonsaxad":"1608140","nonsung":"1608136","nonthaburi":"1608133","nonthiy":"1608131","nontkhaburi":"1608133","nontoron":"2990140","nontron":"2990140","nontronh":"2990140","noo":"589933","nooksack":"5804860","noom timur":"8403200","noorabad":"1453226","noordbergum":"2749992","noorder-paarl":"3363613","noordhorn":"2749875","noordwijk-binnen":"2749812","noordwijk":"2749812","noordwijkerhout":"2749811","noordwolde":"2749807","nooriabad":"1453226","noormarkku":"644436","noorooma":"2155750","noorābād":"1453226","noosa heads":"2155135","noosa":"2155135","nop":"739600","nopal":"3528620","nopala":"3800500","nopaltepec":"3517225","nopalucan de la granja":"3522645","nopalucan":"3522645","nopeog":"4776222","nopphitam":"7510889","noqinsk":"520068","nor armavir":"616352","nor bayazet":"616599","nor dzhrashen":"616724","nor geghi":"616341","nor gekhi":"616341","nor gyugh":"616340","nor gyukh":"616340","nor sasunik":"823793","nor yerznka":"823791","nor-bajaset":"616599","nora springs":"4869045","nora":"3172227,2689471","norabats'":"799614","norabats’":"799614","noraduz":"616361","noragugume":"3172212","norak'aghak'":"616062","norak":"1220905","norakert":"616359","norak’aghak’":"616062","norala":"1697577","noramarg":"616356","norashen":"799614,616345,146858","norath":"2862164","noratus":"616361","noravoka":"4839822","norba caesarina":"2520611","norbello":"3172211","norberg":"2689452","norbergby":"2689452","norbolin":"2028351","norbukyungze":"1280425","norbukyungzê":"1280425","norbury":"2641465","norbusa":"8046614","norcacia":"3673811","norcasia":"3673811","norceping":"2688368","norcia":"3172208","norco":"5377199,4335326","norcopia":"2688368","norcross":"4212888","nord odalen":"3140452","nord-libre":"3023955","nord-odal":"3140452","nord":"6293082","nordborg":"2616176","nordburg":"2616176","nordby":"2616172","norddajkh":"2862136","norddeich":"2862136,2862135","norddorf":"2862131","norden":"2862118","nordendorf":"2862106","nordenham":"2862104","nordenkham":"2862104","nordenkhame":"2862104","norderbrarup":"2862093","norderheistedt":"2862065","norderney":"2862041","nordershtedt":"2862026","nordershtet":"2862026","norderstapel":"2862027","norderstedt stadt":"2862026","norderstedt":"2862026","norderwohrden":"2862011","norderwöhrden":"2862011","nordfjordeid":"3144369","nordfjordeidet":"3144369","nordhackstedt":"2861996","nordhalben":"2861990","nordhastedt":"2861988","nordhausen":"2861982,2990120","nordheim":"2861973,2861971","nordheimsund":"3144110","nordhofen":"2861951","nordholz":"2861939","nordhorn":"2861934","nordhouse":"2990120","nordingra":"2689344","nordingrå":"2689344","nordiya":"294003","nordiyah":"294003","nordiyya":"294003","nordkhauzen":"2861982","nordkhorn":"2861934","nordkirchen":"2861923","nordleda":"2861919","nordmaling":"2689336","nordovicum":"2641181","nordrach":"2861881","nordsehl":"2861873","nordshtemmen":"2861866","nordstemen":"2861866","nordstemmen":"2861866","nordurthing":"2629833","norduz":"298940","nordwalde":"2861847","nore sundet":"3144113","nore":"3172226","norena":"3115363","norenberg":"3097871","noresund":"3144113","noreña":"3115363","norfok":"4776222","norfolk county":"6089125","norfolk":"4945453,5073965,5128862,4776222","norfolkas":"4776222","norfolko":"4776222","norgouits":"2641181","norheim":"2861830","norheimsund":"3144110","noria del borrego (norias)":"4021452","noria":"1278373","norich":"2641181","noridzas":"2641181","noridzh":"4839843,2641181,5129359","noridžas":"2641181","noril'sk":"1497337","norilskoe":"1497337","noril’sk":"1497337","norimberg":"2861650","norimberga":"2861650","norimberk":"2861650","norimbèrga":"2861650","noritchi":"2641181","norken":"2861829","norland":"4166066","norlina":"4482264","norma":"3172204","normal'naja":"4903780","normal":"4903780","norman wells":"6089245","norman":"4543762","normana":"4543762","normandin":"6089179","normandy park":"5804885","normandy":"2641447,4400737","normanhurst":"2155092","normanton":"2641443","normanvill":"2064565","normanville":"2064565,2990107","norovlin":"2028351","norowlin":"2028351","norra asum":"2689192","norra åsum":"2689192","norrcheping":"2688368","norrchjoping":"2688368","norre aaby":"2616368","norre aby":"2616368","norre alslev":"2616365","norre hvalso":"2616308","norrent-fontes":"2990096","norrfjarden":"604006","norrfjärden":"604006","norridge":"4903803","norridgewock":"4973430","norris city":"4245780","norris":"4645799","norristown":"5203506","norrkoeping":"2688368","norrkoping":"2688368","norrköping":"2688368","norrkøping":"2688368","norrmark":"644436","norroy-les-pont-a-mousson":"2990090","norroy-lès-pont-à-mousson":"2990090","norroy":"2990090","norrsundedet":"2688255","norrsundet":"2688255","norrtaeljen kunta":"2688250","norrtalje":"2688250","norrtel'e":"2688250","norrtelge":"2688250","norrtelje":"2688250","norrtälje":"2688250","norrtäljen kunta":"2688250","nors adams":"4945486","nors andover":"4832272","nors kaldvehll":"5101901","nors plehjtt":"5697939","norsehmpton":"4945819","norsepinga":"2688368","norsfild":"5039675","norsh'oping":"2688368","norsheping":"2688368","norsin":"313331","norsiopingas":"2688368","norsjo":"2688172","norsjoe":"2688172","norsjö":"2688172","norsjø":"2688172","norsoup":"2135517","norstedt":"2861820","norsup":"2135517","norsuup":"2135517","nort adams":"4945486","nort bej":"6089426","nort bend":"5804915","nort majami":"4166232","nort york":"6091104","nort-bej":"6089426","nort-bervik":"2641419","nort-jork":"6091104","nort-majami":"4166232","nort-platt":"5697939","nort-shor":"2185964","nort-sur-erdre":"2990085","nort":"2990085","nortamptonas":"2641430","nortelandia":"3456248","nortele":"2688250","nortelje":"2688250","norteljė":"2688250","nortelândia":"3456248","norten-hardenberg":"2861817","nortershausen":"2861815","nortfild":"5039675","nortgempton":"2641430,4945819","north adams":"4945486","north adelaide":"8469169","north alamo":"4714990","north altona":"8298607","north amherst":"4945497","north amityville":"5128884","north andover":"4832272","north andrews gardens":"4166096","north apollo":"5203519","north arlington":"5101873","north atlanta":"4212937","north auburn":"5377266","north augusta":"4589368","north aurora":"4903818","north babylon":"5128886","north ballston spa":"7258360","north baltimore":"5164653","north barrington":"4903830","north bath":"4973457","north battleford":"6089404","north bay shore":"5128898","north bay village":"4166105","north bay":"6089426","north beach haven":"4503289","north beach":"2064546,4363831","north bel air":"4363836","north belle vernon":"5203529","north bellmore":"5128904","north bellport":"5128905","north bend":"5074013,5742974,5804915","north bennington":"5239101","north bergen":"5101879","north berwick":"4973463,2641419","north bethesda":"4363843","north bibb":"4080395","north booval":"7932655","north boston":"5128914","north braddock":"5203537","north bradley":"2641413","north branch":"5003617,5039421","north branford":"4839636","north bridgewater":"2174079","north brighton":"2207611","north brookfield":"4945548","north brooksville":"4166124","north browning":"5668939","north caldwell":"5101901","north canton":"5164706","north cape may":"4503299","north catasauqua":"5203618","north cave":"2641404","north charleroi":"5203609","north charleston":"4589387","north chicago":"4903862","north chicopee":"4945588","north college hill":"4519853","north collins":"5128996","north conway":"5090347","north corbin":"4302681","north cowichan":"6089661","north creek":"5804953","north crossett":"4124039","north de land":"4166154","north decatur":"4212992","north deland":"4166154","north druid hills":"4212995","north eagle butte":"5767488","north east":"4363889,5203634","north eastham":"4945608","north edwards":"5377380","north el monte":"5377381","north elmham":"2641370","north elmsall":"2641369","north english":"4869136","north fair oaks":"5377389","north falmouth":"4945622","north ferriby":"2641356","north fond du lac":"5264814","north fork village":"4519883","north fort myers":"4166195","north fremantle":"2064510","north ft. myers":"4166195","north gates":"5129050","north gauhati":"1261186","north gauhāti":"1261186","north glendale":"5377613","north granby":"4839692","north great river":"5129057","north grosvenor dale":"4839697","north guwahati":"1261186","north guwāhāti":"1261186","north haledon":"5101922","north hampton":"5090383","north hartsville":"4589426","north haven":"2154949,4839704","north haverhill":"5090375","north hero":"5239188","north highlands":"5377640","north hill":"2641337","north hills":"5129093","north hollywood":"5377654","north hudson":"5264862","north ipswich":"7932658","north judson":"4924242","north kansas city":"4400860","north kensington":"4363960","north key largo":"4166208","north kingstown":"5223672","north kingsville":"5164812","north la crosse":"5264870","north lakeport":"7261991","north lakeville":"4945659","north lakhimpur":"1261181","north lancing":"2641319","north las vegas":"5509403","north lauderdale":"4166222","north laurel":"4363964","north leigh":"2641315","north lewisburg":"5164826","north liberty":"4869195,4924243","north lindenhurst":"5129125","north little rock":"4124112","north logan":"5779025","north luffenham":"2641310","north madison":"4262293,5164840","north manchester":"4924246","north mankato":"5039537","north massapequa":"5129134","north melbourne":"7281804","north merrick":"5129141","north miami beach":"4166233","north miami":"4166232","north middletown":"5101935","north muskegon":"5003811","north myrtle beach":"4589446","north narrabeen":"6693769","north new hyde park":"5129147","north newton":"4276386","north oaks":"5039554","north ogden":"5779036","north olmsted":"5164862","north palm beach":"4166253","north patchogue":"5129157","north pekin":"4903975","north pembroke":"4945700","north peoria":"4903976","north perth":"6090405","north petherton":"2641284","north plainfield":"5101938","north plains":"5743413","north platte":"5697939","north plymouth":"4945707","north pole":"5870294","north port":"4166274","north potomac":"4363990","north prairie":"5264924","north providence":"5223681","north puyallup":"5805248","north queensferry":"2641280","north randall":"5164891","north reading":"4945734","north redington beach":"4166288","north richland hills":"4715292","north richmond":"5377775","north ridgeville":"5164903","north river shores":"4166293","north riverside":"4904002","north rock springs":"5833892","north royalton":"5164916","north ryde":"7281782","north saanich":"6090579","north saint paul":"5039587","north salt lake":"5779068","north sarasota":"4166298","north scituate":"4945764,5223685","north sea":"5129210","north seekonk":"4945769","north shields":"2641267","north shore":"7280463,2185964,4776469","north side village":"3580575","north side":"3580575","north sioux city":"5230076","north smithfield":"5223687","north spearfish":"7259417","north springfield":"4776472","north stamford":"4839745","north star":"4143897","north sunderland":"2641253","north sydney":"2154855","north syracuse":"5129242","north terre haute":"4262311","north tidworth":"2637310","north tonawanda":"5129245","north tunica":"4439033","north turramurra":"2154849","north tustin":"5404122","north uist":"8299849","north upi":"1680233","north vacherie":"4335535","north valley stream":"5129248","north valley":"5481793","north vancouver":"6090785","north vanlaiphai":"1261173","north vernon":"4262318","north versailles":"5203785","north wales":"5203788","north walsham":"2641233","north wantagh":"5129254","north warren":"5203791","north webster":"4924273","north weeki wachee":"7260514","north westport":"4945808","north wildwood":"4503313","north wilkesboro":"4482577","north windham":"4973717","north wonthaggi":"2154826","north yelm":"5805317","north york":"6091104,4560048","north zanesville":"4519923","northa pleta":"5697939","northallerton":"2641435","northam":"2064550,2641434","northampton":"2064549,2641430,4945819,5203804","northamptonia":"2641430","northborough":"2641416,4945840","northbridge":"4945848","northbrook":"4904056,4519924","northcliff":"4715410","northcrest":"4715411","northeast ithaca":"7258390","northeim":"2861814","northempton":"2641430","northern cambria":"5203837","northfield":"4904094,4302761,4945878,5039675,5090459,5101962,5164998,5239281","northgate":"4519938","northglenn":"5433124","northiam":"2641331","northlake":"4904102,4589508,4715447","northlakes":"4482621","northleach":"2641318","northmead":"2154913","northolt":"2641290","northorpe":"2641287","northport":"4080555,4973781,5129290","northridge":"5377985,4519951","northumberland":"5090464,5203859","northvale":"5101967","northview":"5003952","northville":"5003956,5129314","northwest harbor":"5129325","northwest harborcreek":"7258393","northwest harwich":"7257737","northwest harwinton":"7257391","northwest ithaca":"7258394","northwich":"2641224","northwick":"2641224","northwood":"2641217,4869369,5090470,5165069","northwoods":"4400962","nortkerque":"2990087","nortkhajm":"2861814","nortkhamptun":"2641430,4945819","nortkhempton":"2641430,4945819,5203804","nortmoor":"2861807","norton canes":"2641193","norton center":"7257739","norton shores":"5004005","norton":"884141,2641207,4276452,4945911,5165087,4776585","nortonville":"4302778","nortorf":"2861804","nortrup":"2861802","nortumberlend":"5203859","nortvicas":"2641224","nortvich":"2641224","nortvičas":"2641224","norucha":"3172208","noruok":"5377995","noruolk":"4839822","norutohaimu":"2861814","norutohauzen":"2861982","norvalk":"4839822","norvenich":"2861801","norvic":"2641181","norvich":"4839843,2641181","norvika":"4839843","norville":"3007582","norviç":"2641181","norvok":"5377995,4839822","norvoka":"4839822","norvolk":"4839822,5165101","norvolkas":"5377995,4839822","norvulin":"2028351","norwalk":"5377995,4839822,4869386,5165101","norway":"4973840,5004016","norwell":"4945936","norwich":"4839843,2641181,5129359","norwood (historical)":"5039796","norwood young america":"5039798","norwood":"4945952,4482693,5101978,5129364,4519995,4560057","norymberga":"2861650","norzagaray":"1697497","norzugaray":"1697497","norðurþing":"2629833","norşin":"313331","noršiopingas":"2688368","noršēpinga":"2688368","nosaelleoteon":"2641435","nosaempeuteon":"2641430","nosate":"3172202","nosen":"2861788","noseuaedeomseu":"4945486","noseuliteullog":"4124112","noshiro":"2128867","noshirominato":"2128867","noshopingu":"2688368","nosilovo":"624612","nosir khisrav":"1221583","nosiro":"2128867","nosirskij":"2128867","nosislav":"3069720","nosivka":"699917","noslac":"672167","noslau":"3069720","nosovka":"699917","nosowka":"699917","nosratabad-e bala":"122111","nosratabad-e pa'in":"122111","nosratabad":"122111","noss ziona":"294074","nossa senhora da conceicao de itanhaem":"3460791","nossa senhora da conceição de itanhaém":"3460791","nossa senhora da gloria":"3456240","nossa senhora da glória":"3456240","nossa senhora da graca de povoa e meadas":"2264351","nossa senhora da graça de póvoa e meadas":"2264351","nossa senhora da luz do aterrado":"3458333","nossa senhora da luz":"3374120","nossa senhora das dores":"3456234","nossa senhora de campos do rio real":"3446400","nossa senhora do desterro":"3463237","nossa senhora do destêrro":"3463237","nossa senhora do itanhem":"3460785","nossa senhora do monte de itapicuru da praia":"3465713","nossa senhora do monte":"2265494","nossa senhora do socorro":"3456223","nossa senhora dos prazeres do inhambupe":"3464100","nossa":"3170237","nossebro":"2688131","nossen":"2861788","nossendorf":"2861787","nossentiner hutte":"2861784","nossentiner hütte":"2861784","nossikon":"6294551","nostang":"2990080","nostorf":"2861774","nosubei":"6089426","nosucharusuton":"4589387","nosufirudo":"5039675","nosuyoku":"6091104","nosy varika":"1058080","nosyn":"2861788","not":"5378044","nota":"2126250","notabile":"2562746","notaresco":"3172199","notasamu":"2126250","notasan":"2126250","noteland":"3144534","nothoorn":"2861934","nothweiler":"2861755","noto":"2523998","notodden":"3144075","notoonnuur":"1515468","notre dame de liesse":"2998460","notre dame station":"934232","notre dame":"934232,8469294","notre-dame-de-bondeville":"2990064","notre-dame-de-foy-de-rochefort":"2787948","notre-dame-de-gravenchon":"2990056","notre-dame-de-l'ile-perrot":"6091369","notre-dame-de-l'île-perrot":"6091369","notre-dame-de-mesage":"2990047","notre-dame-de-monts":"2990045","notre-dame-de-mésage":"2990047","notre-dame-de-riez":"2990043","notre-dame-de-sanilhac":"2990042","notre-dame-des-landes":"2990039","notre-dame-des-prairies":"6091422","notre-dame-du-bon-conseil":"6091436","notre-dame":"2990042,2990064,2990045","notse":"2364752","notsukeushi":"2129537","notsé":"2364752","nottensdorf":"2861743","nottfeld":"2861739","nottigham":"2641170","notting hill":"2154796","nottingamu":"2641170","nottingem":"2641170","nottingham":"2641170,5090496","nottleben":"2861736","notton":"2641167","nottuln":"2861733","nottwil":"2659436","notzingen":"2861721","nou barris":"6252065","nou":"2139521","noua sulitsa":"699285","nouaceur":"2541210","nouadhibou":"2377457","nouaille-maupertuis":"2990012","nouaille":"2990012","nouaillé-maupertuis":"2990012","nouaillé":"2990012","nouakchat":"2377450","nouakchot":"2377450","nouakchott":"2377450","nouaksot":"2377450","nouan-le-fuzelier":"2990007","nouan":"2990007","nouaseur":"2541210","nouatja":"2364752","nouaxot":"2377450","noubbel":"166331","noubbol":"166331","nouc hai":"1571725","noui causanii":"618120","noui căuşanii":"618120","noukoualopha":"4032402","noum":"5870133","noumea":"2139521","nouméa":"2139521","nouna":"2357163","nououk":"3421319","noupoort":"969582","nousiainen":"644326","nousis":"644326","nousty":"2989970","nouvelle france":"934229","nouvelle-rochelle":"5128549","nouvieau york":"5128581","nouvion-en-ponthieu":"2989957","nouvion-sur-meuse":"2989953","nouvion":"2989953,2989957","nouvoitou":"2989952","nouzilly":"2989945","nouzon":"2989943","nouzonville":"2989943","nou~oku":"5377995","nouâdhibou":"2377457","nov charjui":"1219649","nov chārjui":"1219649","nov pokrovka":"1527497","nov\" grad\"":"519336","nov\"grad\"":"519336","nov-delhio":"1261481","nov-jorko":"5128581","nov-orleano":"4335045","nov-orleans":"4335045","nov. bujan":"517218","nov.burasy":"517172","nov.chigla":"519777","nov.egorlyk":"516801","nov.gorki":"517144","nov.igirma":"2019004","nov.leushino":"517503","nov.malykla":"518619","nov.praga":"699802","nov.rogachik":"516875","nov.sanzhary":"698927","nov.starodub":"698869","nov.svet":"698861","nov.tavolzhanka":"519473","nov.usman'":"519447","nov.vodolaga":"699777","nov.zaimka":"1496588","nov":"1514856,3348313","nova aurelia":"4335045","nova aurora":"3456196","nova bana":"3058498","nova belgrado":"787607","nova beluno":"3447598","nova borova":"699882","nova bukovica":"3190264","nova bystrice":"3069706","nova cerekev":"3069705","nova civitas vindobonensis":"2761353","nova crnja":"787621","nova cruz":"3393876","nova dantzig":"3467978","nova delhi":"1261481","nova deli - na'i dilli":"1261481","nova deli - नई दिल्ली":"1261481","nova deli":"1261481","nova dili":"1645457","nova dubnica":"3058496","nova era":"3456176","nova floresta":"3393867","nova freixo":"1047660","nova friburgo":"3456166","nova goa":"1260607","nova gorica":"3194452","nova goricja":"3194452","nova gradiska":"3194449","nova gradisska":"3194449","nova gradiška":"3194449","nova granada":"3456164","nova iguacu":"3456160","nova iguassu":"3456160","nova iguassú":"3456160","nova iguaçu":"3456160","nova iorque":"5128581","nova kakhovka":"699839","nova kanjiza":"787600","nova kanjiža":"787600","nova lamego":"2372532","nova lesna":"724026","nova levante - welschnofen":"3172192","nova levante":"3172192","nova lima":"3456147","nova lisboa":"3348313","nova londres":"4839416,5164352","nova londrina":"3456146","nova majachka":"699823","nova mayachka":"699823","nova mehsta":"3194351","nova mesta":"3194351","nova milanese":"3172191","nova moldava":"672912","nova nkoritsa":"3194452","nova odesa":"699811","nova odessa":"3456138","nova olimpia":"3456137","nova olinda do norte":"3393838","nova olinda":"3455913","nova olímpia":"3456137","nova orleaes":"4335045","nova orleans":"4335045","nova orleáns":"4335045","nova orleães":"4335045","nova paka":"3069669","nova palanka":"3204674","nova petropolis":"3456127","nova petrópolis":"3456127","nova ponente - deutschnofen":"3172190","nova ponente":"3172190","nova praga":"699802","nova praha":"699802","nova prata":"3456125","nova redonda":"3346015","nova redondo":"3346015","nova role":"3069662","nova roma":"3403534","nova ruda":"3090768","nova russas":"3393832","nova santa medianeira":"3457359","nova sarca":"785252","nova sarča":"785252","nova schwechat":"2765388","nova siri":"3172187","nova sol":"3090764","nova sola":"3090764","nova soure":"3456115","nova sul'":"3090764","nova ujgradiska":"3194449","nova ulma":"2863941,5039173","nova ushicja":"699899","nova ushytsya":"699899","nova varos":"3194407","nova varosh":"3194407","nova varoš":"3194407","nova vas":"3194403","nova vcelnice":"3069648","nova venecia":"3456110","nova venécia":"3456110","nova vicosa":"3456102","nova vila do campo maior":"3390901","nova viçosa":"3456102","nova vodolaga":"699777","nova vodolaha":"699777","nova york":"5128581","nova zagora":"728742","nova újgradiska":"3194449","nova-delhi":"1261481","nova-gorica":"3194452","nova-iguasu":"3456160","nova-lesna":"724026","nova-lima":"3456147","nova-ruda":"3090768","nova-sul'":"3090764","nova-york":"5128581","novabad":"1220936","novaberd":"787589","novace":"782169","novaci streini":"672151","novaci-straini":"672151","novaci-străini":"672151","novaci":"672151,677072,672156,787624","novacii-straini":"672151","novacii-străini":"672151","novacë":"782169","novae":"726534","novaesium":"2864118","novafeltria":"3172195","novaglia":"3194422","novaja brjan'":"2019009","novaja brjan":"2019009","novaja bukhtarma":"1520660","novaja chara":"2055822","novaja chigla":"519777","novaja derevnja":"519711","novaja igirma":"2019004","novaja ladoga":"519630","novaja ljada":"519621","novaja ljalja":"1497276","novaja majna":"519611","novaja maka":"469186","novaja malykla":"518619","novaja odessa":"699811","novaja tavolzhanka":"519473","novaja tsjara":"2055822","novaja usman'":"519447","novaja zaimka":"1496588","novaky":"3058493","novalaise":"3172193,2989941","novaledo":"3172194","novaleisa":"3172193","novales":"3115349","novalesa":"3172193","novalja":"3194422","novallas":"1697489,3115346","novallaso":"1697489","novalèisa":"3172193","novara di sicilia":"2523994","novara sicilia":"2523994","novara":"3172189","novarcum":"5101798","novare":"3172189","novaria":"3172189","novasela":"782163","novate mezzola":"3172185","novate milanese":"3172184","novate":"3172185","novato":"5378044","novaya annenskaya":"519062","novaya ataga":"517191","novaya balakhna":"579514","novaya belokurikha":"1510502","novaya bogdanovka":"699657","novaya borovaya rudnya":"699882","novaya borovaya":"699882","novaya bryan'":"2019009","novaya bryan’":"2019009","novaya bukhara":"1217180","novaya bukhtarma":"1520660","novaya chara":"2055822","novaya chigla":"519777","novaya derevnya":"519711","novaya dmitriyevskaya":"518928","novaya dzhereliyevskaya":"518907","novaya eushta":"1489597","novaya fedorovka":"699607","novaya igirma":"2019004","novaya igrima":"2019004","novaya kakhova":"699839","novaya kakhovka":"699839","novaya ladoga":"519630","novaya lugovaya":"1496976","novaya lyada":"519621","novaya lyalya":"1497276","novaya maka":"469186","novaya malykla":"518619","novaya mayachka":"699823","novaya mayna":"519611","novaya odessa":"699811","novaya pis'menka":"536162","novaya pis'myanka":"536162","novaya pis’menka":"536162","novaya pis’myanka":"536162","novaya praga":"699802","novaya saratovka":"585346","novaya sysoyevka":"2018857","novaya tavolzhanka":"519473","novaya ushitsa":"699899","novaya usman'":"519447","novaya usman’":"519447","novaya utka":"517744","novaya vodolaga":"699777","novaya vorontsovka":"699034","novaya zaimka":"1496588","novaya zyryanka":"2119283","novaya":"2018925","novazzano":"2659433","novbeogrado":"787607","nove benatky":"3079514","nove davidkovo":"699015","nove davydkove":"699015","nove davydkovo":"699015","nove dilli":"1261481","nove hrady":"3069493","nove mesto na morave":"3069465","nove mesto nad metuji":"3069466","nove mesto nad vagom":"3058477","nove mesto nad vahom":"3058477","nove mesto pod siatrom":"715839","nove mesto pod smrkem":"3069464","nove mesto":"3069464","nove misto":"699761","nove mjasto ljubavsko":"3090613","nove mjasto lubavske":"3090613","nove s'ventsyany":"594067","nove sedlo":"3069437","nove straseci":"3069431","nove sve":"3191802","nove syrovice":"3069429","nove s’ventsyany":"594067","nove varpno":"3090590","nove veseli":"3069422","nove zamki":"3058472","nove zamky":"3058472","nove šve":"3191802","nove-misto":"699761","nove-mjasto-ljubavs'ke":"3090613","nove-mjasto-ljubavske":"3090613","nove-mjasto":"763661,3090613","nove-varpno":"3090590","nove":"3172183","noveant-sur-moselle":"2989938","noveant":"2989938","novedrate":"6534443","novel'da":"2513195","novelda":"2513195","noveleta":"1697486","novellara":"3172177","novello":"3172176","novensis moesia civitas":"726534","noventa di piave":"3172175","noventa padovana":"6534220","noventa vicentina":"3172173","noventa":"3172173","noves":"6697592,2989935","novgorod-seversk":"699753","novgorod-severskij":"699753","novgorod-severskiy":"699753","novgorod-sivers'kij":"699753","novgorod":"519336","novgorodka":"699756","novgradets":"726591","novhi sada":"3194360","novhorod-sivers'kyy":"699753","novhorod-sivers’kyy":"699753","novhorodka":"699756","novi banovci":"787612","novi becej":"787610","novi belgrad":"787607","novi belgrade":"787607","novi beograd":"787607","novi bečej":"787610","novi bilokorovichi":"698943","novi bilokorovici":"698943","novi bilokorovychi":"698943","novi bug":"698953","novi di modena":"3172172","novi dvor gdanski":"3090502","novi dvor mazovjecki":"763556","novi dvor mazovski":"763556","novi dvora gdanska":"3090502","novi dvora gdaņska":"3090502","novi dvora mazovecka":"763556","novi grad":"3203647","novi hodas":"2771870","novi itebej":"787602","novi karlovci":"787601","novi karlovec":"787601","novi knezevac":"787600","novi kneževac":"787600","novi kozarci":"787598","novi kozjak":"787597","novi krichim":"726890","novi ligure":"3172170","novi pazar":"728734,787595","novi pazaras":"787595","novi sad":"3194360","novi sadas":"3194360","novi sant":"3194360","novi sanzari":"698927","novi sanzhary":"698927","novi seher":"3194358","novi senzhari":"698927","novi slankamen":"787592","novi sonca":"763534","novi sonch":"763534","novi sonča":"763534","novi sopot":"666433","novi targ":"763523","novi targa":"763523","novi travnik":"3192236","novi troani":"698921","novi troyany":"698921","novi velia":"3172169","novi vinodol'ski":"3194355","novi vinodol":"3194355","novi vinodolski":"3194355","novi vukovar":"3187047","novi zagreb":"3209408","novi šeher":"3194358","novi-beograd":"787607","novi-jichin":"3069305","novi-ligure":"3172170","novi-padej":"787274","novi-paza":"728734","novi-pazar":"787595","novi-sad":"3194360","novi":"3203647,3194355,5004062","novicastrum":"2659496","novichikha":"1497220","novicja":"699746","noviercas":"3115335","noviforum":"3085047","novigentum rotroudi":"2990272","noviglio":"6535767","novigrad":"3194379","novij ariciv":"698852","novij bug":"698953","novij dvur-gdans'kij":"3090502","novij orlean":"4335045","novij sad":"3194360","novij sonch":"763534","novij starodub":"698869","novij svit":"698861","novij targ":"763523","novij ul'm":"2863941","novij-dvir-mazovec'kij":"763556","noviki":"519168","novikovo":"1497215","noviliacum ad sequanam":"2990611","novillars":"2989929","novillas":"3115334","noville-les-bois":"2789999","noviodunum":"2659422","noviomum":"2989877","novioritum":"2990355","novisada":"3194360","novita":"3673783","novitsa":"699746","novitsjikha":"1497220","novjorko":"5128581","novkastelo":"2155472","novki":"519168","novliki":"2122783","novlya":"523186","novmumbajo":"6619347","novo aksai":"583674","novo aleksandrovsko":"592891","novo alexandrovsk":"592891","novo aripuana":"3663142","novo aripuanã":"3663142","novo bayazet":"616599","novo bellamo":"3447598","novo brdo":"787589","novo bug":"698953","novo chardzhou":"1219649","novo cruzeiro":"3456070","novo exu":"3400541","novo granaoa":"3456164","novo hamburg":"3456068","novo hamburgo":"3456068","novo horizonte":"3456060,3472138","novo igirma":"2019004","novo kakhovka":"699839","novo kaushani":"618120","novo laredo":"3522551","novo lino":"3393792","novo mesto":"3194351","novo milosevo":"792945","novo miloševo":"792945","novo nikolayevsk":"2018904","novo oriente":"3393783,3454131","novo oskol":"516931","novo pokrovzkoye":"699328","novo redondo":"3346015","novo selo":"3194334,2770788,728709,787574","novo traian":"698921","novo trajan":"698921","novo'kievsk":"2021644","novo-aneny":"617702","novo-annenskiy":"519062","novo-bryanskoye":"2019009","novo-chardzhuy":"1219649","novo-dimitrievskoe":"565979","novo-karachayevskiy":"517009","novo-kholmogory":"581049","novo-kievsku":"2021644","novo-kiyevskoye":"2021644","novo-kocherdyk":"1489137","novo-kubanskaya":"518682","novo-kuybuyshev":"518659","novo-kuybyshevskiy":"518659","novo-leushkovskoye":"518643","novo-lisino":"562450","novo-lyubino":"1500125","novo-mariinsk":"2127202","novo-mariinskiy":"2127202","novo-markovka":"701792","novo-mikhaylovka":"518585","novo-mikhaylovskaya":"518585","novo-nikolaevsk":"1496747","novo-nikolaievsk":"1496747","novo-nikolayevskaya":"518488","novo-nikolaïevsk":"1496747","novo-pashkyskiy":"559752","novo-peredelkino":"511510","novo-petrovskoye":"2018888","novo-pokrovskiy":"2018888,518333","novo-pokrovskoye":"1527497,699328","novo-popovka":"701588","novo-selo":"731822","novo-senaki":"612053","novo-senzhary":"698927","novo-starodub":"698869","novo-sventsyany":"594067","novo-troitskiy promysel":"2027184","novo-troitskiy":"517836","novo-troitskoye":"1527360","novo-tsurukhaitui":"2017646","novo-tsurukhaytuy":"2017646","novo-tsurukhaytuyevskiy":"2017646","novo-tsurukhtuyevskiy":"2017646","novo-ukrainka":"699706","novo-ulakly":"703646","novo-urainka":"699078","novo-urgench":"1512473","novo-usman'":"519447","novo-usman’":"519447","novoagansk":"1497210","novoaleksandrovsk":"592891,519106","novoaleksandrovskaya":"519106","novoalekseevka":"699706","novoalekseevskaja":"519085","novoaleksejevskaja":"519085","novoalekseyevka":"703317","novoalekseyevskaya":"519085","novoalexandrovsk":"519106","novoaltajsk":"1497173","novoaltaysk":"1497173","novoannenka":"519062","novoannenskaya":"519062","novoanninskij":"519062","novoanninskiy":"519062","novoardonskoye":"563551","novoarkhangel'sk":"699680","novoarkhangel’sk":"699680","novoarkhanhel's'k":"699680","novoarkhanhel’s’k":"699680","novoasbest":"1497163","novoazbest":"1497163","novoazovs'k":"699675","novoazovsk":"699675","novoazovskoye":"699675","novobatajsk":"519033","novobataysk":"519033","novobejsugskaja":"519015","novobelokataj":"519027","novobelokatay":"519027","novobelokurikha":"1510502","novoberda":"787589","novoberde":"787589","novobessergenevka":"519016","novobessergenovka":"519016","novobeysugskaya":"519015","novobiriljussy":"1508260","novobirilyussy":"1508260","novobirjusinskij":"1497142","novobiryusinskaya":"1497142","novobiryusinskiy":"1497142","novoblagodarnoe":"519005","novoblagodarnoje":"519005","novoblagodarnoye":"519005","novobod":"1220936","novobogdanivka":"699657","novobogdanovka":"699657","novobohdanivka":"699657","novoburejskij":"2018964","novobureyskiy":"2018964","novobërda":"787589","novobërdë":"787589","novoceboksarsk":"518976","novocerkask":"518970","novocerkaska":"518970","novocerkaskas":"518970","novocerkassk":"518970","novocheboksarsk":"518976","novocheremshansk":"518972","novocherkas'k":"518970","novocherkask":"518970","novocherkassk":"518970","novochernorechenskij":"1497132","novochernorechenskiy":"1497132","novochernorechenskoye":"1497132","novocserkasszk":"518970","novoderevjankovskaja":"518944","novoderevyankovskaya":"518944","novodmitrievskaja":"518928","novodmitrijevskaja":"518928","novodmitriyevskaya":"518928","novodolinskiy":"1520627","novodolīnskīy":"1520627","novodugino":"518912","novoduginskaya":"518912","novodvinsk":"518909","novodzherelievskaja":"518907","novodzherelievskaya":"518907","novodzhereliyevskaya":"518907","novodzjerelijevskaja":"518907","novoe devjatkino":"517577","novoe leushino":"517503","novoe mamon":"520564","novofedorovka":"699607","novogagatli":"518897","novogagatlinskoe":"518897","novogagatlinskoye":"518897","novogard":"3090558","novogarda":"3090558","novogardia magna":"519336","novogeorgievsk":"692087","novogeorgiyevsk":"692087","novogireevo":"518879","novogireyevo":"518879","novogornyj":"1497095","novogornyy":"1497095","novogorod-severskiy":"699753","novograd volynski":"699553","novograd-volins'kij":"699553","novograd-volynsk":"699553","novograd-volynskij":"699553","novograd-volynskiy":"699553","novogroudok":"624785","novogroznenskii":"518851","novogroznenskij":"518851","novogroznenskiy":"518851","novogrud":"763600","novogrudek":"624785","novogrudok":"624785","novogurovskij":"518845","novogurovskiy":"518845","novohrad-volyns'kyy":"699553","novohrad-volyns’kyy":"699553","novoishimskij":"1535379","novoishimskiy":"1535379","novojavorivs'k":"8468760","novojavorovsk":"8468760","novoje atlasjevo":"827792","novoje devjatkino":"517577","novokajakent":"518764","novokayakent":"518764","novokazalinsk":"1516789","novokhoperk":"518745","novokhopersk":"518745","novokhopjorsk":"518745","novokhopërsk":"518745","novokhovrino":"518740","novokivsk":"2021644","novokiyevsk":"2021644","novokizhinginsk":"2018930","novokizjinginsk":"2018930","novokoeznetsk":"1496990","novokorsunskaja":"518701","novokorsunskaya":"518701","novokouznetsk":"1496990","novokruchininskij":"2018925","novokruchininskiy":"2018925","novokrutsjininskij":"2018925","novokubansk":"518682","novokubanskiy":"518682","novokubanskoe":"518682","novokubanskoye":"518682","novokujbyshevsk":"518659","novokujbysjevsk":"518659","novokuybyshevsk":"518659","novokuz'minki":"518657","novokuznec'k":"1496990","novokuzneck":"1496990","novokuznecka":"1496990","novokuzneckas":"1496990","novokuznetk":"1496990","novokuznetsk":"1496990","novokuznețk":"1496990","novokuznjeck":"1496990","novokuzněck":"1496990","novokuzņecka":"1496990","novokuz’minki":"518657","novolabinskaja":"518652","novolabinskaya":"518652","novolakskoe":"518648","novolakskoje":"518648","novolakskoye":"518648","novoleushkovskaja":"518643","novoleushkovskaya":"518643","novoleusjkovskaja":"518643","novoli":"3172168","novollas":"1697489","novoloki":"523161","novolugovoe":"1496976","novolugovoje":"1496976","novolugovoye":"1496976","novolugovskoye":"1496976","novolukoml'":"624494","novolukoml’":"624494","novomaklakovo":"1500607","novomalorossijskaja":"518621","novomalorossiskaya":"518621","novomalorossiyskaya":"518621","novomalykla":"518619","novomichurinsk":"518602","novomikhajlovskij":"518585","novomikhaylovskiy":"518585","novomikhaylovskoye":"518585","novomikhurinsk":"518602","novomikolaivka":"699413","novominskaja":"518568","novominskaya":"518568","novominskoye":"518568","novomirgorod":"699453","novomishastovski":"518540","novomitsjurinsk":"518602","novomoskovs'k":"699445,518557","novomoskovsk i russland":"518557","novomoskovsk":"699445,518557","novomoskovskas":"518557","novomoskovs’k":"699445","novomykolayivka":"699410,699413","novomyrhorod":"699453","novomyshastovskaja":"518540","novomyshastovskaya":"518621","novomysjastovskaja":"518540","novonazyvayevka":"1497932","novonazyvayevskoye":"1497932","novonikol'sk":"2018904","novonikol'skoye":"2018904","novonikolaevka":"699410","novonikolaevsk":"1496747","novonikolaevskij":"518488","novonikolajevskij":"518488","novonikolayevka":"699410,1520590,699413","novonikolayevsk":"1496747","novonikolayevskaya":"699675","novonikolayevskiy":"518488","novonikolsk":"2018904","novonikol’sk":"2018904","novonikol’skoye":"2018904","novonukutskij":"2015469","novonukutskiy":"2015469","novooleksiivka":"699706","novooleksiyivka":"699706","novoomskij":"1496889","novoomskiy":"1496889","novoorsk":"518418","novoostankino":"514284","novopashiyskiy":"559752","novopavloskaya":"518383","novopavlovka":"2018896","novopavlovsk":"518383","novopavlovskaya":"518383","novopavoskaya":"518383","novopetrovskoe":"518346","novopetrovskoje":"518346","novopetrovskoye":"518346","novopis'myanka":"536162","novopiscovo":"518344","novopistsovo":"518344","novopis’myanka":"536162","novoplatnikovskaya":"518341","novoplatnirovskaja":"518341","novoplatnirovskaya":"518341","novopodrezkovo":"518337","novopokrovka":"699329,699328,2018888,518333,534838","novopokrovskaja":"518325","novopokrovskaya":"518325","novopokrovskoye":"2018888,518333","novopokurofuskoe":"2018888","novopolock":"624784","novopolockas":"624784","novopolotsk":"624784","novopskov":"699311","novoradomsk":"3087497","novorajchikhinsk":"2018882","novorajtsjikhinsk":"2018882","novoraychikhinsk":"2018882","novorosijsk":"518255","novorossiejsk":"518255","novorossiisk":"518255","novorossijsk":"518255","novorossisk":"518255","novorossiysk":"518255","novorozhdestvenskaja":"518249","novorozhdestvenskaya":"518249","novorozjdestvenskaja":"518249","novorudnyj":"518246","novorudnyy":"518246","novorzhev":"518236","novorzjev":"518236","novosadovoe":"580218","novosadovoye":"580218","novosahtinsk":"517963","novosaratovka":"585346","novosavidovsk":"461704","novosedlice":"3069398","novosedly":"3069395","novosel'e":"624418","novosel'skoe":"584298","novosel'skoye":"584298","novosel'ye":"624418","novosel":"3184588","novosela":"782163,3184588","novoselci":"731675","novosele":"782163,3184588","novoselec":"3194344","novoseletskoye":"518209","novoseleznevo":"1492827","novoseleznjovo":"1492827","novoseleznëvo":"1492827","novoselica":"699272","novoselice":"700295","novoselicja":"699285","novoselickoe":"518209","novoselitsa":"699285,699272,700295","novoselitskoe":"518209","novoselitskoje":"518209","novoselitskoye":"518209","novoselj":"3184588","novosella":"3184588","novoseltsi":"731675","novoselytsya":"699285,699272","novoselë":"782163,3184588","novosel’skoe":"584298","novosel’skoye":"584298","novosel’ye":"624418","novosemejkino":"517992","novosemeykino":"517992","novosergeyevka":"517982","novosergeyevskoye":"517982","novosergievka":"517982","novosergijevka":"517982","novosergiyevka":"517982","novoshakhtinsk":"517963","novoshakhtinskij":"2018864","novoshakhtinskiy":"2018864","novoshcherbinovskaya":"517959","novosheshminsk":"517958","novoshherbinovskaja":"517959","novosibir'sku":"1496747","novosibir":"1496747","novosibirs'k":"1496747","novosibirscum":"1496747","novosibirsk":"1496747","novosibirska":"1496747","novosibirskaj":"1496747","novosibirskas":"1496747","novosibirskij akademgorodok":"1512086","novosibirskiy nauchnyy tsentr":"1512086","novosibirsko":"1496747","novosil'":"517947","novosil":"517947","novosilikatnyj":"1496739","novosilikatnyy":"1496739","novosil’":"517947","novosimpirsk":"1496747","novosineglazovskij":"1496738","novosineglazovskiy":"1496738","novosjakhtinskij":"2018864","novosjesjminsk":"517958","novosjtsjerbinovskaja":"517959","novosmolinskij":"517926","novosmolinskiy":"517926","novosokol'niki":"517921","novosokolniki":"517921","novosokol’niki":"517921","novospasovka":"698316","novospasovskaya":"698316","novospasskoe":"517897","novospasskoje":"517897","novospasskoye":"698316,517897","novosseltzi":"731675","novossibirsk":"1496747","novosuvorovskaya":"470338","novosuvorovskoye":"470338","novosysoevka":"2018857","novosysojevka":"2018857","novosysoyevka":"2018857","novoszibirszk":"1496747","novotavolzhanka":"519473","novotcherkassk":"518970","novoterskij":"841363","novoterskiy":"841363","novotiraspol'skiy":"617053","novotiraspol’skiy":"617053","novotitarovskaja":"517842","novotitarovskaya":"517842","novotjerkassk":"518970","novotroick":"517836","novotroickaja":"517813","novotroitsk":"517836","novotroitskaja":"517813","novotroitskaya":"517813","novotroitskoye":"699100,517813","novotroyan":"698921","novotroyits'ke":"699100","novotroyits’ke":"699100","novotseboksarsk":"518976","novotserkassk":"518970","novotsjeboksarsk":"518976","novotsjeremsjansk":"518972","novotsjerkassk":"518970","novotsjernoretsjenskij":"1497132","novotyryshkino":"1496651","novotyrysjkino":"1496651","novotšeboksarsk":"518976","novotšerkassk":"518970","novoukrainka":"699078,517769","novoukrainsk":"699078","novoukrainskij":"517769","novoukrainskiy":"517769","novoukrainskoe":"517767","novoukrainskoje":"517767","novoukrainskoye":"517767","novoukrayinka":"699078","novoul'janovsk":"517766","novoul'yanovsk":"517766","novouljanovsk":"517766","novoul’yanovsk":"517766","novoural'sk":"1538636","novoural’sk":"1538636","novoutkinsk":"517744","novouzensk":"517739","novovarshavka":"1496633","novovarsjavka":"1496633","novovasil'yevka":"699061","novovasilevka":"699061","novovasilivka":"699061","novovasil’yevka":"699061","novovasylivka":"699061","novovelichkovskaja":"517725","novovelichkovskaya":"517725","novovelitsjkovskaja":"517725","novovjazniki":"517698","novovladykino":"473127","novovoionezhskiy":"517716","novovolins'k":"699035","novovolyns'k":"699035","novovolynsk":"699035","novovolynskiy":"699035","novovolyns’k":"699035","novovoroncovka":"699034","novovoronezh":"517716","novovoronezhskiy":"517716","novovoronezj":"517716","novovorontsovka":"699034","novovyazniki":"517698","novoy bryan":"2019009","novoyavorivs'k":"8468760","novoye atlashevo":"827792","novoye davidkovo":"699015","novoye davydkovo":"699015","novoye devyatkino":"517577","novoye khovrino":"518740","novoye leushino":"517503","novoye medvezhino":"624400","novoye semeykino":"517992","novoye tyryshkino":"1496651","novozaimka":"1496588","novozavedennoe":"517303","novozavedennoje":"517303","novozavedennoye":"517303","novozavedenskoye":"517303","novozavidovskij":"461704","novozavidovskiy":"461704","novozhareliyevskaya":"518907","novozibkov":"517269","novozybkov":"517269","novoçerkassk":"518970","novoĉeboksarsk":"518976","novoĉerkassk":"518970","novočeboksarsk":"518976","novočerkask":"518970","novočerkaska":"518970","novočerkaskas":"518970","novočerkassk":"518970","novoīshīmskīy":"1535379","novoŝaĥtinsk":"517963","novošahtinsk":"517963","novo’kievsk":"2021644","novr-gala":"523206","novr-giala":"523206","novr-ġala":"523206","novra":"2154787","novska":"3194319","novszka":"3194319","novu sadu":"3194360","novugorodo":"519336","novum castellum":"2641673","novum comum":"3178229","novum eboracum":"5128581","novum forum siculorum":"665004","novum laredum":"3522551","novum lovanium":"2792073","novum monasterium":"2864475","novus burgus":"2641598","novus mons":"787589","novus portus":"4839366","novu~ara":"3172189","novu~aredo":"3172194","novu~areza":"3172193","novu~e":"3172183","novu~ochebokusarusuku":"518976","novu~ocherukassuku":"518970","novu~odovu~insuku":"518909","novu~okuzunetsuku":"1496990","novu~omosukofusuku":"518557","novu~oshibirusuku":"1496747","novy belehrad":"787607","novy bor":"3069381","novy budzov":"3069377","novy budžov":"3069377","novy bug":"698953","novy buyan":"517218","novy bydzov":"3069377","novy bystrice":"3069706","novy dvor":"763556","novy hrozenkov":"3069308","novy jicin":"3069305","novy knin":"3069300","novy malin":"3069290","novy oskol":"516931","novy rogachik":"516875","novy s'verzhen'":"624297","novy sad":"3194360","novy sonch":"763534","novy starodub":"698869","novy sverzhan'":"624297","novy svet":"698861,541629","novy svyerzhan'":"624297","novy svyerzhan’":"624297","novy s’verzhen’":"624297","novy targ":"763523","novy-duninuv":"3090528","novy-dvur-gdan'skij":"3090502","novy-dvur-mazovecki":"763556","novy-dvur-mazoveckij":"763556","novy-sonch":"763534","novy-stav":"3090470","novy-targ":"763523","novy-yegorlyk":"516801","novy-zhmigrud":"763519","novye aneny":"617702","novye atagi":"517191","novye burasy":"517172","novye cherjomushki":"517161","novye gorki":"517144","novye kuz'minki":"517121","novye lapsary":"866053","novye ljady":"517111","novye milford":"5101766","novye zori":"1539142","novyezori":"1539142","novyi bayaset":"616599","novyi svit":"698866","novyj afon":"615912","novyj berlin":"4245481,5128465","novyj brajton":"5203116","novyj bujan":"517218","novyj chirkej":"869345","novyj egorlyk":"516801","novyj hutor":"558418","novyj karachaj":"517009","novyj karatsjaj":"517009","novyj khushet":"802921","novyj khusjet":"802921","novyj kostek":"858716","novyj nekouz":"516935","novyj orlean":"4335045","novyj oskol":"516931","novyj rogachik":"516875","novyj sulak":"858712","novyj svet":"698866","novyj tsjirkej":"869345","novyj uojan":"2018813","novyj urengoj":"1496511","novyj urgal":"2047258","novyj zagan":"2018811","novyj":"6422876,5004062","novytsya":"699746","novyy afon":"615912","novyy ardon":"563551","novyy atagi":"517191","novyy belokatay":"519027","novyy bug":"698953","novyy buh":"698953","novyy buyan":"517218","novyy chirkey":"869345","novyy el'ton":"563495","novyy el’ton":"563495","novyy gorodok":"699706","novyy karachay":"517009","novyy karanlug":"146969","novyy kargasok":"1504382","novyy khushet":"802921","novyy kocherdyk":"1489137","novyy kostek":"858716","novyy krasnoostrov":"577907","novyy kryazhim":"532092","novyy lyubuzh":"624318","novyy margelan":"1514019","novyy nekouz":"516935","novyy oskol":"516931","novyy rogachik":"516875","novyy sandets":"763534","novyy sokur":"1491525","novyy sonch":"763534","novyy starodub":"698869","novyy sulak":"858712","novyy sverzhen'":"624297","novyy sverzhen’":"624297","novyy svet":"698861,698866,541629","novyy svit":"698861,698866","novyy targ":"763523","novyy turtkul'":"1513092","novyy turtkul’":"1513092","novyy uoyan":"2018813","novyy urengoy":"1496511","novyy urgal":"2047258","novyy yarychev":"698852","novyy yarychiv":"698852","novyy yegorlyk":"516801","novyy zagan":"2018811","novyy":"6422876,2014624","novyye aneny":"617702","novyye atagi":"517191","novyye belokorovichi":"698943","novyye belorovichi":"698943","novyye burassy":"517172","novyye burasy":"517172","novyye cheremushki":"517161","novyye cherëmushki":"517161","novyye gorki":"517144","novyye kaushany":"618120","novyye keushani":"618120","novyye kholmogory":"581049","novyye kuz'minki":"517121","novyye kuz’minki":"517121","novyye lapsary":"866053","novyye lyady":"517111","novyye petushki":"509697","novyye s'ventsyany":"594067","novyye sanzhary":"698927","novyye senzhary":"698927","novyye shuli":"712576","novyye svenchany":"594067","novyye s’ventsyany":"594067","novyye troki":"593871","novyye troyany":"698921","novyye zori":"1539142","novzka":"3194319","nová baňa":"3058498","nová bystřice":"3069706","nová cerekev":"3069705","nová dubnica":"3058496","nová lesná":"724026","nová paka":"3069669","nová role":"3069662","nová včelnice":"3069648","nováky":"3058493","nové benátky":"3079514","nové dillí":"1261481","nové hrady":"3069493","nové mesto nad váhom":"3058477","nové mesto pod šiatrom":"715839","nové město na moravě":"3069465","nové město nad metují":"3069466","nové město pod smrkem":"3069464","nové město":"3069464","nové sedlo":"3069437","nové strašecí":"3069431","nové syrovice":"3069429","nové veselí":"3069422","nové zámky":"3058472","novéant-sur-moselle":"2989938","novéant":"2989938","novés":"6697592","novî sad":"3194360","nový bor":"3069381","nový bydžov":"3069377","nový bystřice":"3069706","nový bělehrad":"787607","nový hrozenkov":"3069308","nový jičín":"3069305","nový knín":"3069300","nový malín":"3069290","nový sad":"3194360","nový targ":"763523","now dahanak":"1132127","now dahānak":"1132127","now danak":"1132127","now dānak":"1132127","now shahr":"121959","now zad":"1131649","now zād":"1131649","nowa deba":"763783","nowa dęba":"763783","nowa gora":"3090798","nowa góra":"3090798","nowa ruda":"3090768","nowa sagora":"728742","nowa sarzyna":"763765","nowa slupia":"763764","nowa sol":"3090764","nowa sól":"3090764","nowa słupia":"763764","nowa wies leborska":"3090690","nowa wies wielka":"3090673","nowa wies":"3090759","nowa wieś lęborska":"3090690","nowa wieś wielka":"3090673","nowa wieś":"3090759","nowaiyon":"2989877","nowaji=ru=guran":"2990189","nowaji=ru=rowa":"2990188","nowaji=ru=sekku":"2990187","nowajowa":"764067","nowanagar":"1269317","nowanuggur":"1269317","nowata":"4544025","nowe bojszowy":"3103001","nowe brzesko":"763676","nowe dabe":"3100545","nowe grocholice":"7576667","nowe lipiny":"766237","nowe miasteczko":"3090616","nowe miasto k. plonska":"763661","nowe miasto k. płońska":"763661","nowe miasto lubawskie":"3090613","nowe miasto nad metuja":"3069466","nowe miasto nad metują":"3069466","nowe miasto nad pilica":"763659","nowe miasto nad pilicą":"763659","nowe miasto nad warta":"3090612","nowe miasto nad wartą":"3090612","nowe miasto":"592828,763661,3090612","nowe okmiany":"596719","nowe ostrowy":"7576143","nowe siolo":"763650","nowe sioło":"763650","nowe skalmierzyce":"3090597","nowe swieciany":"594067","nowe warpno":"3090590","nowe święciany":"594067","nowe-miasto":"3090613","nowe":"3090660","nowgorod sewerski":"699753","nowgorod":"519336","nowgradez":"726591","nowi dwor":"3090502","nowi dwór":"3090502","nowi pasar":"728734","nowi soncz":"763534","nowi sóncz":"763534","nowi wedel":"3100148","nowo aleksandrowskaja":"519106","nowo radomsko":"3087497","nowo ruda":"3090768","nowo sokolniki":"517921","nowo troizkoje":"2027184","nowo-alexandrowskaja":"519106","nowo-nikolajewskaja":"699675","nowo-selo":"728709","nowo-swieciany":"594067","nowo-swięciany":"594067","nowo-titarowskaja":"517842","nowo-tschigla":"519777","nowoaleksandrowsk":"519106","nowoalexandrowsk":"519106","nowochopersk":"518745","nowoczerkask":"518970","nowodwinsk":"518909","nowodwor":"763608","nowodwór":"763608","nowogard":"3090558","nowograd wolynsk":"699553","nowogrod bobrzanski":"3090553","nowogrod wielki":"519336","nowogrod":"763600","nowogrodek pomorski":"3090552","nowogrodek":"624785","nowogrodziec":"3090551","nowogród bobrzański":"3090553","nowogród wielki":"519336","nowogród":"763600","nowogródek pomorski":"3090552","nowogródek":"624785","nowoja-ladoga":"519630","nowokeu":"5377995,4839822,5165101","nowokoeznetsk":"1496990","nowokusnezk":"1496990","nowokuznieck":"1496990","nowokuźnieck":"1496990","nowominskaja":"518568","nowomoskowsk":"518557","nowomyschastowskaja":"518540","nowopolock":"624784","nowopołock":"624784","noworossiisk":"518255","noworossijsk":"518255","noworosyjsk":"518255","noworshew":"518236","nowoschachtinsk":"517963","nowoschtscherbinowskaja":"517959","nowosibirsk":"1496747","nowosibirski":"1496747","nowosielce-gniewosz":"763585","nowosielce":"763586","nowosselzi":"731675","nowosybirsk":"1496747","nowosybkoff":"517269","nowoszachtynsk":"517963","nowoszachtyńsk":"517963","nowotroick":"517836","nowotroizk":"517836","nowotscheboksarsk":"518976","nowotscherkask":"518970","nowotscherkassk":"518970","nowotsjerkassk":"518970","nowowelitschkowskaja":"517725","nowra":"2154787","nowshehra":"1168864","nowshera cantonment":"1341204","nowshera":"1168864","nowthen":"5281144","nowy belgrad":"787607","nowy duninow":"3090528","nowy duninów":"3090528","nowy dwn gdanski":"3090502","nowy dwor gdanski":"3090502","nowy dwor mazowiecki":"763556","nowy dwor":"763556,3090502","nowy dwór gdański":"3090502","nowy dwór mazowiecki":"763556","nowy dwór":"763556,3090502","nowy jiczyn":"3069305","nowy jork":"5128581","nowy kaweczyn":"769364","nowy kawęczyn":"769364","nowy korczyn":"763545","nowy orlean":"4335045","nowy rembertow":"760503","nowy rembertów":"760503","nowy ruda":"3090768","nowy sacz":"763534","nowy sad":"3194360","nowy staw":"3090470","nowy suncz":"763534","nowy sącz":"763534","nowy sůncz":"763534","nowy targ":"763523","nowy tomysl":"3090452","nowy tomyśl":"3090452","nowy wisnicz":"763521","nowy wiśnicz":"763521","nowy zamek":"3090553","nowy zmigrod":"763519","nowy żmigród":"763519","nowy.sontc":"763534","nowyi bug":"698953","nowé dãbé":"3100545","nowé warpno":"3090590","nowògard":"3090558","noxvil":"4634946","noy kuren":"509437","noyabr'sk":"1496503","noyack":"5129395","noyada":"7279746","noyakert":"174805","noyal-muzillac":"2989920","noyal-pontivy":"2989918","noyal-sur-vilaine":"2989914","noyal":"2989914","noyan somon":"2030465","noyan sume":"2030465","noyan sumu":"2030465","noyan":"2030465","noyant-la-gravoyere":"2989909","noyant-la-gravoyère":"2989909","noyant-sous-le-lude":"2989913","noyant":"2989913","noyarey":"2989906","noyelles-godault":"2989901","noyelles-les-vermelles":"2989899","noyelles-lez vermelles":"2989899","noyelles-lès-vermelles":"2989899","noyelles-sous-lens":"2989897","noyelles":"2989899","noyemberyan":"616333","noyen-sur-sarthe":"2989890","noyen":"2030465,2989890","noyers-sur-cher":"2989879","noyers":"2989879","noyida":"7279746","noyin somon":"2030465","noykhauzen":"557906","noyon suma":"2030465","noyon":"2030465,2989877","noyta perunakar":"6954929","noyta":"7279746","noyën":"2030465","noz":"1496990","nozad":"1131649","nozaj-jurt":"516780","nozanputon":"2641430","nozate":"3172202","nozay":"2989874,2989876","nozdrzec":"763517","nozhaj-jurt":"516780","nozhan-le-rotru":"2990272","nozhan-sjur-marn":"2990265","nozhan-sjur-uaz":"2990264","nozhay-yurt":"516780","nozhayt-yurt":"516780","nozhen le rotru":"2990272","nozieg":"2989876","nozjaj-jurt":"516780","nozjo":"2989874","noé":"2990294","noéyon":"2989877","noëmoeti":"1633903","noāmundi":"1261242","noćajski salaš":"3191339","noġamirzin-yurt":"571702","noşlac":"672167","noşratābād-e bālā":"122111","noşratābād-e pā’īn":"122111","noşratābād":"122111","nožaj-jurt":"516780"}