{"zi bo shi":"1785286","zi bo":"1785286","zi bu zhen":"1783750","zi bu":"1783750","zi cheng zhen":"1783731","zi cheng":"1783731","zi dui si ka wo la":"3080414","zi ge re lai ci":"3080231","zi gong shi":"1783745","zi gong":"1783745","zi hu zhen":"7065291","zi hu":"7065291","zi jin xiang":"8561473","zi jin zhen":"1783730","zi jin":"1783730,8561473","zi ke tan zhen":"1783724","zi ke tan":"1783724","zi li xiang":"8416207","zi li":"8416207","zi liang ping":"1783720","zi liang xiang":"1783720","zi liang yao zu xiang":"6422018","zi liang":"6422018","zi ling pu zhen":"1783719","zi ling pu":"1783719","zi nuo yi mo":"3061344","zi qiu zhen":"1783709","zi qiu":"1783709","zi run xiang":"1783708","zi run":"1783708","zi shan zhen":"1783707","zi shan":"1783707","zi shi zhen":"1940989,1919515","zi shi":"1940989,1919515","zi shui xiang":"1783701","zi shui":"1783701","zi tong jie dao":"1783700","zi tong zhen":"1811871,6975018","zi tong":"1811871,6975018,1783700","zi tuo zhen":"1279435","zi tuo":"1279435","zi wo er ni ke":"3186246","zi wo lei":"2743477","zi wo qie fu":"3080101","zi wo qie nie ci":"3080102","zi wo tu fu":"3080071","zi wu jie ban":"1783694","zi wu":"1783694","zi xi xiang":"7064787","zi xi":"7064787","zi xiao zhen":"1798384","zi xiao":"1798384","zi xing shi":"1783688","zi xing":"1783688","zi yang cheng guan zhen":"1783682","zi yang qu":"8548695","zi yang xian":"1783682","zi yang zhen":"1790863","zi yang":"1790863","zi you shi":"2409306","zi yuan":"1814345","zi yun zhen":"7061735","zi yun":"7061735","zi zhao xiang":"8405710","zi zhao":"8405710","zia' bar":"111058","ziabar (gaskar)":"111058","ziabar":"111058","ziabera":"111058","ziamet":"146386","ziano di fiemme":"3163876","ziano piacentino":"3163875","ziano":"3163875","ziar nad hronom":"3056523","ziarat shah maqsud":"1120627","ziarat-e shah maqsud":"1120627","ziarat-shakh-maksud":"1120627","ziarat":"1162094","ziaziakon":"735375","ziba'":"106909","zibak":"1120616","zibdani":"172059","zibdānī":"172059","zibello":"3163874","ziber-murize":"781158","zibido san giacomo":"3163872","zibo":"1785286","zibu zhen":"1783750","zibu":"1783750","ziburu":"3024979","zibër-murizë":"781158","zic":"3868326","zicheng zhen":"1783731","zicheng":"1783731","zichidorf":"787032","zichifalva":"787032","zichihaza":"787032","zichiháza":"787032","zichow":"2804630","zichydorf":"787032","zichyfalva":"787032","zichyhaz":"787032","zichyház":"787032","zicifalva":"787032","zickhusen":"2804616","zidi":"744051","zidikan":"315758","zidikân":"315758","zidlochovice":"3061472","zidoscica":"675254","zidošcica":"675254","zidul":"662201","ziduri":"662204,662201","zidurile":"662201","ziebice":"3080226","ziebingen":"3101255","zieciuki":"766783","ziegelheim":"2804549","ziegendorf":"2804399","ziegenhain":"2804391","ziegenhals":"3099169","zielenogorsk":"463830","zielenogradsk":"463828","zielenzig":"3084237","zielitz":"2804318","zielona gora":"3080165","zielona góra":"3080165","zielona nkora":"3080165","zielonka":"753276","zielonki":"3080156","ziembice":"3080226","ziemetshausen":"2804313","zierbena":"3125077","zierenberg":"2804297","zierow":"2804285","ziersdorf":"2760575","ziertheim":"2804283","zierzow":"2804282","ziesar":"2804279","ziesendorf":"2804268","ziethen":"2804255,2804254","ziezmariai":"592778","ziezmariu":"592778","zifa pie ivetas":"3016078","zifta":"346030","ziftá":"346030","zig":"2243940","zigapor":"739070","zigburg":"2832521","zigdi":"744051","zigen":"2832495","zighartice":"3063385","zighinkor":"2243940","zigincor":"2243940","ziginshor":"2243940","ziginsoras":"2243940","ziginĉor":"2243940","ziginšoras":"2243940","zigiunchor":"2243940","zigmaringen":"2832232","zignago":"6534438","zigong":"1783745","zigopor":"739070","zigos":"733749","zigri":"744051","ziguinchor":"2243940","zigós":"733749","zihle":"3061462","zihu zhen":"7065291","zihu":"7065291","zihuatanejo":"3979673","zihuri":"3125058","zijin xiang":"8561473","zijin zhen":"1783730","zijin":"1783730,8561473,1783731","zijtaart":"2743877","zike":"2824461","ziketan":"1783724","ziki":"287814","zil'c":"2765036","zil":"737054","zilah":"662334","zilair":"462626","zilang xiang":"1783720","zilang":"1783720","zile":"737054","zilfi":"107781","zili xiang":"8416207","zili":"8416207","ziliahova":"734977","ziliang yaozuxiang":"6422018","ziliang":"6422018","ziliangping":"1783720","zilina":"3056508","zilingpu zhen":"1783719","zilingpu":"1783719","ziliten":"2208485","ziliáhova":"734977","zillah":"5816719","zillegem":"2783308","zillehem":"2783308","zillertal":"2771725","zillingdorf":"2760564","zillingtal":"2760563","zillisheim":"2967139","zillmere":"6943555","zilshausen":"2804208","ziltendorf":"2804207","zilupe":"453850","zilupes":"453850","ziluppe":"453850","zilwaukee":"5015723","zima":"2012484","zimandu nou":"662197","zimandul-nou":"662197","zimapan":"3514031","zimapán":"3514031","zimare":"2353257","zimaré":"2353257","zimatlan de alvarez":"3514027","zimatlan":"3514027","zimatlán de álvarez":"3514027","zimatlán":"3514027","zimbolija":"675223","zimbor":"662195","zimborul-mare":"662195","zimborul":"662195","zimbreasca":"662193","zimdorf":"2804034","zimella":"3163870","zimerat":"2832023","zimern":"2832013","zimi":"2402689","zimme":"1153671","zimmerat":"2832023","zimmerbude":"485660","zimmerman":"5033783","zimmern ob rottweil":"2804159","zimmern unter der burg":"2804157","zimmern":"2832013,2804161","zimmernsupra":"2804158","zimmerscheid":"2804155","zimmerschied":"2804155","zimmersheim":"2967137","zimmi":"2402689","zimmicelele":"662186","zimmé":"1153671","zimnica":"662187","zimnice":"662187","zimnicea":"662187","zimnicele":"662186","zimnicelele":"662186","zimnich":"662187","zimniçe":"662187","zimone":"3163869","zimony":"783920","zimovniki":"462522","zimunay":"1529429","zin'kiv":"687292","zin":"2660253","zinabel'kirkhen":"2765019","zinacantan":"3514026","zinacantepec":"3518221","zinacantán":"3514026","zinacatan":"3514026","zinacatepec":"3518221,3517795","zinacatán":"3514026","zinapecuaro de figueroa":"3979665","zinapecuaro":"3979665","zinapécuaro de figueroa":"3979665","zinapécuaro":"3979665","zinarie":"2353257","zinarié":"2353257","zinasco":"3163867","zinat":"2525973","zincig":"2831852","zindah jan":"1120711","zindah jān":"1120711","zindajan":"1120711","zindajān":"1120711","zindel'fingen":"2831948","zindelfingen":"2831948","zinder":"2437798","zingem":"2783215","zingen":"2831924","zingolweni":"994408","zingst":"2804135","zinguilucan":"3516642","zinguinhor":"2243940","ziniare":"2353257","ziniaré":"2353257","zinjibar":"69426","zinjibār":"69426","zinna":"2804121","zinnik":"2786420","zinnowitz":"2804109","zinov'evsk":"705812","zinov'yevsk":"705812","zinovievsk":"705812","zinov’evsk":"705812","zinov’yevsk":"705812","zinsheimas":"2831872","zinskhajm":"2831872","zintan":"2218963","zinten":"588673","zintenhof":"588673","zintán":"2218963","zinzikon":"6295111","zin’kiv":"687292","zio":"2831580","ziolochovice":"3061472","zion":"281184,4917358,5220463","zionsville":"4267336","ziordia":"3125007","zipacon":"3665544","zipacón":"3665544","zipaquira":"3665542","zipaquirá":"3665542","zipari":"444350","ziparion":"444350","zippnow":"3083908","zipári":"444350","zipárion":"444350","ziqiu zhen":"1783709","ziqiu":"1783709","zir":"2615006,2657916","zira":"584562,7645176","ziraki":"1467505","zirandara":"3979647","zirandaro":"3979647","zirardova":"752967","ziravik":"322462","zirc":"3042536","zirchow":"2804051","zirgan":"462467","ziri":"3186450","zirja":"584562","zirklach":"3202711","zirknitz":"3202709","zirkow":"2804041","zirkwitz":"3101879","zirl":"2760523","zirnau":"3076413","zirndorf":"2804034","zirnovon":"735879","ziro":"304134,1252668","zirona":"3188089","ziroudani":"1090640","zirovnica":"3186442","zirovnice":"3061437","ziruk `alaqahdari":"1435007","ziruk `alaqehdari":"1435007","ziruk":"1435007","zirun xiang":"1783708","zirun":"1783708","zirya":"584562","ziryanovsk":"1516438","zirzow":"2804022","zirándaro":"3979647","zirǝ":"584562","zirə":"584562","zisena":"3178957","zishan zhen":"1783707","zishan":"1783707","zishi zhen":"1940989,1919515","zishi":"1940989,1919515","zishui xiang":"1783701","zishui":"1783701","zislow":"2804018","zistafoni":"610864","zistersdorf":"2760510","zisèna":"3178957","zit":"2804008","zitacuaro":"4004885","zitaraves":"2764988","zitava":"2804008","zitawa":"2804008","zitenice":"3061431","zitiste":"783887","zitlala":"3514021","zitlaltepec":"3815329","zitlaltepetl":"3815329","zitlaltépec":"3815329","zito":"1279435","zitomir":"686967","zitomiria":"686967","zitong jiedao":"1783700","zitong zhen":"1811871,6975018","zitong":"1811871,6975018,1783700","zitorada":"783880","zitoraga":"783880","zitose":"783877","zitoste":"783877","zittau":"2804008","zittersdorf":"2764988","zittert":"2747203","zituo zhen":"1279435","zituo":"1279435","zitácuaro":"4004885","ziuda bolivar":"3645532","ziuda de panama":"3703443","ziudá bolívar":"3645532","ziudá de panamá":"3703443","ziukajka":"461756","ziuzelskij":"1484889","zivarik":"323930","ziveca":"3079855","zivinice gornje":"3200059","zivinice":"3186423,3186422","zivint":"320582","ziway":"325579","ziwu jieban":"1783694","ziwu":"1783694","ziwuzhen":"1783694","zix":"2012530","zixi xiang":"7064787","zixi":"7064787","zixiao zhen":"1798384","zixiao":"1798384","zixing shi":"1783688","zixing":"1783688","ziya' bar":"111058","ziyamet":"146386","ziyang chengguanzhen":"1783682","ziyang qu":"8548695","ziyang xian":"1783682","ziyang zhen":"1790863","ziyang":"1790863,1783682,1783683","ziyaret":"297517","ziyuan":"1814345","ziyun zhen":"7061735","ziyun":"7061735","ziywon":"281184","ziza":"250639","zizelic":"3061416","zizelice":"3061416","zizers":"2657916","zizhao xiang":"8405710","zizhao":"8405710","zizhong":"1814919","zizikar":"2035265","zizin":"662181","zizmariai":"592778","zizur nagusia":"3124955","zizurkil":"3124953","zizyo":"2045005","zizyō":"2045005","ziáziakon":"735375","ziārat shāh maqsūd":"1120627","ziārat":"1162094","zičifalva":"787032","ziębice":"3080226","zięciuki":"766783","ziğdi":"744051","ziğri":"744051"}